[{"id": "1", "title": "Vous qui sur la terre habitez", "url": "https://drive.google.com/uc?export=download&id=1DP_ogB5zF19g8o_4uxQ_W4X65zZKKYcG"}, {"id": "2", "title": "Les cieux, en chaque lieu", "url": "https://drive.google.com/uc?export=download&id=1TEfyYIW90ffTZRXaP7U_vyI-Z_YebRLk"}, {"id": "3", "title": "Dieu me conduit", "url": "https://drive.google.com/uc?export=download&id=1PUfyN0kRfeOLSEHa8LNPHAGSa34OadvW"}, {"id": "4", "title": "Comme un cerf alt\u00e9r\u00e9 brame", "url": "https://drive.google.com/uc?export=download&id=1EQd8ZcQVpiZmiX4GGAGdGm-4ucEfPipM"}, {"id": "5", "title": "Mis\u00e9ricorde et gr\u00e2ce", "url": "https://drive.google.com/uc?export=download&id=1yt38U9eGEp40V69htohzAB6oV2d9ETe1"}, {"id": "6", "title": "Peuples, venez, et qu'on entende", "url": "https://drive.google.com/uc?export=download&id=1UqC0a2XorXwzouYccn3ncbpi44Qp3N_v"}, {"id": "7", "title": "Que Dieu se montre seulement", "url": "https://drive.google.com/uc?export=download&id=14N2sFTDGgC8uJ2IHPtZe8a8vo6flAQ14"}, {"id": "8", "title": "L'\u00e2me de douleur atteinte", "url": "https://drive.google.com/uc?export=download&id=1oXZ40VUajhxweu8NfWSiNMtcEd6q_aQQ"}, {"id": "9", "title": "Tu fus toujours, Seigneur", "url": "https://drive.google.com/uc?export=download&id=1O0EPzExw4lqjJ8LWn_ttR65N06USCfBI"}, {"id": "10", "title": "B\u00e9nissons Dieu,", "url": "https://drive.google.com/uc?export=download&id=1S9DNyf1RXDVTmQQ-2VV3iyXsjrrDiFbD"}, {"id": "11", "title": "Heureux celui qui, par un juste choix", "url": "https://drive.google.com/uc?export=download&id=1B8URZF84iOLAZV934lGdsTuBJ1SydxAB"}, {"id": "13", "title": "Je l\u00e8ve les yeux...", "url": "https://drive.google.com/uc?export=download&id=1tcx8_t997H_YlrQnJ2BDy7JHx89dST_U"}, {"id": "14", "title": "Peuples, louez le grand Dieu", "url": "https://drive.google.com/uc?export=download&id=1mEqCGPw0Hyq3q7FeCGCwIuaJY-zo7xm_"}, {"id": "15", "title": "Il faut, grand Dieu...", "url": "https://drive.google.com/uc?export=download&id=1TvprWDx7iB7VQIljkFdTZ-L8Ujo3ihZB"}, {"id": "16", "title": "O P\u00e8re...", "url": "https://drive.google.com/uc?export=download&id=16FaMuwxq6Q94IdbNplimiLejMdVzuluS"}, {"id": "17", "title": "Il a parl\u00e9...", "url": "https://drive.google.com/uc?export=download&id=1dB77nYbWW_E5ofg13cBLzzBCMyzX-2zv"}, {"id": "18", "title": "Dieu fort et grand", "url": "https://drive.google.com/uc?export=download&id=10sM-9VM5ld-TKJzxw_FTRQg8ZIKth4y9"}, {"id": "20", "title": "Grand Dieu, nous te louons", "url": "https://drive.google.com/uc?export=download&id=1_NvgnG4m1GZ4O4tOyvGdOANF4RRQ5uXO"}, {"id": "21", "title": "O toi dont les bienfaits", "url": "https://drive.google.com/uc?export=download&id=15lvzaPksFndBUhmNm_q6CqFpCtgX7lSg"}, {"id": "22", "title": "Qui dit au soleil...", "url": "https://drive.google.com/uc?export=download&id=13ttIhU9jYzrvc3uuMjCmDwVhquMUdcIy"}, {"id": "23", "title": "Seigneur, \u00e0 ton regard...", "url": "https://drive.google.com/uc?export=download&id=14red59tR1UMxfLWEEq17pW3dkSwRHc_F"}, {"id": "24", "title": "All\u00e9luia! Louange \u00e0 Dieu!", "url": "https://drive.google.com/uc?export=download&id=1WK4MrJFrKKLayT5rbmnSso9QLESaCWy3"}, {"id": "25", "title": "Gloire, gloire \u00e0 l'\u00c9ternel!", "url": "https://drive.google.com/uc?export=download&id=1pYdIL7Q5mAkU7sJuqrWDshmqVl-AQ4lv"}, {"id": "26", "title": "Gloire \u00e0 toi, Dieu puissant", "url": "https://drive.google.com/uc?export=download&id=1z0cU4cBlyO2WkqSbCD-ewglQIDJFFD6m"}, {"id": "27", "title": "Adorons le Roi,", "url": "https://drive.google.com/uc?export=download&id=1qainx_8UgNwIGyVlM1-ESHlc1aGVMAPI"}, {"id": "28", "title": "L'\u00c9ternel est ma part", "url": "https://drive.google.com/uc?export=download&id=1pKV0APgChqIVg4DUI1Crb0Bno6-yl_gl"}, {"id": "29", "title": "Grand Dieu puissant...", "url": "https://drive.google.com/uc?export=download&id=13WDRA0EUVWTeih9rVNWTFp3uzF0PSqf9"}, {"id": "31", "title": "J\u00e9hovah! J\u00e9hovah!", "url": "https://drive.google.com/uc?export=download&id=1bRDTkqfFJ1AiyPW_g7AlS2ygzwJElCBv"}, {"id": "32", "title": "Grand Dieu! nous te b\u00e9nissons", "url": "https://drive.google.com/uc?export=download&id=1HfsTYRK567Pus1uE6rd-4_JK1VE2sc4x"}, {"id": "33", "title": "Louez le nom de l'\u00c9ternel", "url": "https://drive.google.com/uc?export=download&id=1MG_yOmgB3r8m1MHhu7ZfvgxqntjvPUEx"}, {"id": "34", "title": "Mon \u00e2me exaltons la gloire", "url": "https://drive.google.com/uc?export=download&id=1TESDmlUFvu66jcBHBtzPP5r6e-G5hv9p"}, {"id": "35", "title": "Que ne puis-je, \u00f4 mon Dieu", "url": "https://drive.google.com/uc?export=download&id=1Sg-0ceFbLAm2_EJiQOj9YJbn-b12f0_k"}, {"id": "36", "title": "Trois fois saint J\u00e9hovah!", "url": "https://drive.google.com/uc?export=download&id=1LFdJgNWpS-xEjR8dwxynDSzc1N0jJQuQ"}, {"id": "37", "title": "Peuples, chantez un saint cantique", "url": "https://drive.google.com/uc?export=download&id=19t9Ll7xCH6RfsphFEviMRbHPUizVW8A0"}, {"id": "38", "title": "Abandonne ta vie", "url": "https://drive.google.com/uc?export=download&id=1d6lxXQHMy9Af_U0UlpIXPqK52iN_SoA-"}, {"id": "39", "title": "Oui, ton amour...", "url": "https://drive.google.com/uc?export=download&id=10Sa1SnVjKa91_B3SgKIEynmHFv7kJsdD"}, {"id": "40", "title": "C'est de toi, P\u00e8re saint...", "url": "https://drive.google.com/uc?export=download&id=1lPuZOTxPbaF8zNUiF9IdtSBw6locccEc"}, {"id": "41", "title": "Gloire \u00e0 toi, Dieu puissant!", "url": "https://drive.google.com/uc?export=download&id=1dNncIapkNf0SVWFdpx9vjjQpRjwRru6A"}, {"id": "42", "title": "A toi la gloire", "url": "https://drive.google.com/uc?export=download&id=1BPMUUXyitFopfE9eVub5zhPeVDzuy09U"}, {"id": "43", "title": "Je veux chanter...", "url": "https://drive.google.com/uc?export=download&id=1cbz9LyUq4jE9bDAtxWalGS_-xO3enGed"}, {"id": "44", "title": "O Dieu! dans ses jours", "url": "https://drive.google.com/uc?export=download&id=1Cpe7sfnPH1GuOSejnewS4UnYQdXrmZ88"}, {"id": "47", "title": "Que ton fid\u00e8le amour", "url": "https://drive.google.com/uc?export=download&id=1WkSy1IGPXvGtZ7RfrnYsDBZtl1WWi3Qi"}, {"id": "48", "title": "Tu m'as aim\u00e9, Seigneur!", "url": "https://drive.google.com/uc?export=download&id=1rAd4ntZK3t0SLzFiBUbanE6x5bqn996H"}, {"id": "49", "title": "Entendez-vous...", "url": "https://drive.google.com/uc?export=download&id=1ROa18q2JvG4-nTWuBcOHsrpipO9UFF53"}, {"id": "50", "title": "Chantons, chantons sans cesse ...", "url": "https://drive.google.com/uc?export=download&id=1VcbVm8X8oMhYVh8lBLQOHTsq66VRcLm1"}, {"id": "51", "title": "Hosanna! B\u00e9ni soit...", "url": "https://drive.google.com/uc?export=download&id=1BsvHtMci_xSCihU0HeNjUQSHaBhnleLm"}, {"id": "52", "title": "Lorsque le ciel retentit...", "url": "https://drive.google.com/uc?export=download&id=1JR_2IDcppJ89dWF4h4NUqLby-CKsWQ0g"}, {"id": "53", "title": "Faisons \u00e9clater notre joie", "url": "https://drive.google.com/uc?export=download&id=1gkn2SpQZb5tEBnX5g0a8rdRVrTpkt439"}, {"id": "54", "title": "O charit\u00e9 supr\u00eame!", "url": "https://drive.google.com/uc?export=download&id=14uXGE4yiW33eD7N1VJz7i7fbgMa5ej93"}, {"id": "55", "title": "O merveilleuse histoire", "url": "https://drive.google.com/uc?export=download&id=183RfNQLC_RYp8px7xJzKF8kSN_KrHZk9"}, {"id": "56", "title": "Oh! que ne pouvons-nous...", "url": "https://drive.google.com/uc?export=download&id=1vvegzEWLHcW51Um3g0F4aptsS4Ymi6S_"}, {"id": "57", "title": "Divin Sauveur", "url": "https://drive.google.com/uc?export=download&id=1DgKs0-GGHDnKI6vWt-wS0eg1QCV4ohR2"}, {"id": "58", "title": "De la divinit\u00e9...", "url": "https://drive.google.com/uc?export=download&id=1NtYgQSSJ9dmTS-LV3e4ty56E5LHbKdPa"}, {"id": "59", "title": "Saint envoy\u00e9 du P\u00e8re", "url": "https://drive.google.com/uc?export=download&id=14ZX21HdDWRM5jnbcgWDezs5WGAV3IKUY"}, {"id": "60", "title": "J'ai quitt\u00e9 le ciel pour toi", "url": "https://drive.google.com/uc?export=download&id=18gUOz_28uKH5J39Q-9FCMAZhDI0VovBV"}, {"id": "61", "title": "Entonnons un saint cantique", "url": "https://drive.google.com/uc?export=download&id=1qACPsWS2YJy3pktbQfrQSTx4uP0aC_6t"}, {"id": "62", "title": "Ma richesse, ma gloire", "url": "https://drive.google.com/uc?export=download&id=145Gz_kDvoQXJ7Jj84SivHIws41WVEuFB"}, {"id": "63", "title": "O bonne nouvelle!", "url": "https://drive.google.com/uc?export=download&id=1bkLjXeGKaH-JgvUbH8lJvtL4wUfkY3Jb"}, {"id": "64", "title": "J'ai suivi J\u00e9sus", "url": "https://drive.google.com/uc?export=download&id=1ITiw3ApBu6SMEMtTTv3fi3MbZbVPYjch"}, {"id": "65", "title": "O fils de Dieu", "url": "https://drive.google.com/uc?export=download&id=1r7MnhO2G4YdUQaL8qBZk6fE1C9sgR503"}, {"id": "66", "title": "Adorable myst\u00e8re", "url": "https://drive.google.com/uc?export=download&id=1dBSlRmnUxuApNS0PcHzZNRo2t_c-O3vx"}, {"id": "67", "title": "Je t'ai suivi sur le calvaire", "url": "https://drive.google.com/uc?export=download&id=1k1q6G9KeqVV5lVXtrMDtCoHJq4-x9uGf"}, {"id": "69", "title": "Sous ton voile d'ignominie", "url": "https://drive.google.com/uc?export=download&id=1JopqroB6u1TqefSW0R03a9QRzu2EOvx0"}, {"id": "70", "title": "Pour qui la mort", "url": "https://drive.google.com/uc?export=download&id=1vwX40mzSguW9mrRrb6jDWU_vw6wrIJUv"}, {"id": "71", "title": "O Christ ! j'ai vu ton agonie", "url": "https://drive.google.com/uc?export=download&id=1nOHu2BjqR6S_laI65-cNfh7GZqi2_nI6"}, {"id": "72", "title": "Pour nous, Christ meurt...", "url": "https://drive.google.com/uc?export=download&id=1l16y2IYGwlofl3voLiJhq11NY1ID_CDA"}, {"id": "73", "title": "R\u00e9dempteur adorable", "url": "https://drive.google.com/uc?export=download&id=1-aW5Rxgw220EUXE66caiCa6NqUxbiPOB"}, {"id": "74", "title": "Sur cette terre", "url": "https://drive.google.com/uc?export=download&id=10Ky9A36Ea9CSDB1IOoIDx6S0tApLDBBW"}, {"id": "75", "title": "Portant sa croix", "url": "https://drive.google.com/uc?export=download&id=1A4xT2sVfvPr2G-1r7wRhK95BG54Adkao"}, {"id": "77", "title": "Il est la-bas, plus haut...", "url": "https://drive.google.com/uc?export=download&id=1V4b9ZvrjxXvvLv_O4Jj9_40SVygKxMUR"}, {"id": "78", "title": "Roi couvert de blessures", "url": "https://drive.google.com/uc?export=download&id=1uhEli9oYoxJL3I5ki-UBxtW8WMvY2cGy"}, {"id": "79", "title": "A celui qui nous a sauv\u00e9s", "url": "https://drive.google.com/uc?export=download&id=1R81z5vJwneF3ToOP4c73tnlzE36oB2pF"}, {"id": "80", "title": "Christ est ressuscit\u00e9!", "url": "https://drive.google.com/uc?export=download&id=1qgwmqrijXumQV13tUoQD9sYsMAFBsqCO"}, {"id": "81", "title": "A toi la gloire!", "url": "https://drive.google.com/uc?export=download&id=1Z52bkRQ1etg2Pw-DRVuWBNYPfAPHqDPV"}, {"id": "82", "title": "Le Sauveur est ressuscit\u00e9", "url": "https://drive.google.com/uc?export=download&id=1NWbEC4LtiNNehsHPg_dK2DqZ2Of-7NvU"}, {"id": "83", "title": "Venez, chr\u00e9tiens", "url": "https://drive.google.com/uc?export=download&id=1ZJx23Vwf3eJohYYhRItUMgPnLk5ekV9k"}, {"id": "85", "title": "J\u00e9sus, agneau de Dieu!", "url": "https://drive.google.com/uc?export=download&id=1wBd5d9Me7ueTw3-Oe-d-WByR0QS_6UuM"}, {"id": "86", "title": "Ah! Si ton sang...", "url": "https://drive.google.com/uc?export=download&id=1AWdqSkhJThcka2eiuYTXX_IlEuqxWwq3"}, {"id": "87", "title": "Qu'elle est douce...", "url": "https://drive.google.com/uc?export=download&id=1Y5vEVst2JvvapQT9typ12Pcj_69MKJe8"}, {"id": "88", "title": "O Seigneur!", "url": "https://drive.google.com/uc?export=download&id=1jEXxgVJ90rvvsoJNTU6fas_OmHt0F-WF"}, {"id": "89", "title": "Oui, pour son peuple", "url": "https://drive.google.com/uc?export=download&id=14xstb9zSYny8RrudfzAwqCXyhh3ijxD6"}, {"id": "90", "title": "Tu m'as lav\u00e9 de mon p\u00e9ch\u00e9", "url": "https://drive.google.com/uc?export=download&id=1iRPE7KJcuBesF3YHhuyE8LCjqECLJGLk"}, {"id": "91", "title": "Tout mon bonheur, Christ...", "url": "https://drive.google.com/uc?export=download&id=1RC4sM4CaKU7cEKZEYMYtYPVK10PBOcjR"}, {"id": "92", "title": "Comme un phare sur la plage", "url": "https://drive.google.com/uc?export=download&id=1weyzJGzRbq5fHnx6YjS78Yr54-ElKllC"}, {"id": "93", "title": "Je la connais, cette joie...", "url": "https://drive.google.com/uc?export=download&id=1dQfdhvPGARLOBc6ZoXYmLvbjcd12t3fl"}, {"id": "94", "title": "Seigneur J\u00e9sus", "url": "https://drive.google.com/uc?export=download&id=1NhGwENxcM8wy-HlPkPR_Jgpjk13ZTYC8"}, {"id": "95", "title": "Je ne sais pourquoi...", "url": "https://drive.google.com/uc?export=download&id=1XXcOjmyfZwtKJGz6ZYckXJm19n73_Hvo"}, {"id": "96", "title": "Je suis scell\u00e9 pour la gloire", "url": "https://drive.google.com/uc?export=download&id=1kR2QA1CEGDOnn_zTcSPwkK4fhvEoWwaa"}, {"id": "97", "title": "J\u00e9sus est notre ami supr\u00eame", "url": "https://drive.google.com/uc?export=download&id=1eCUlVkryWmW0dHf3cTq9BTFAW974ednX"}, {"id": "98", "title": "J\u00e9sus, \u00f4 nom qui surpasse", "url": "https://drive.google.com/uc?export=download&id=18FAO7jfZesBk9b6QhrRPPDOWYKn3Y0LW"}, {"id": "99", "title": "Mon Sauveur m'aime", "url": "https://drive.google.com/uc?export=download&id=1e19SqC0ADdhmr0fTkOwS0xcwB0UMx2s4"}, {"id": "100", "title": "Lorsque dans ma souillure", "url": "https://drive.google.com/uc?export=download&id=1z4YelCs3bIgQd_mOiMm19wbdxRkmjzbW"}, {"id": "101", "title": "M'aimant...", "url": "https://drive.google.com/uc?export=download&id=1aWe_vno-LDYlPUbrcLEfX8btNeNaMaFl"}, {"id": "102", "title": "O Christ dont l'\u00e2me sympathise", "url": "https://drive.google.com/uc?export=download&id=1uq7z9Vyll7JDaheUMur9wi4jJl9qJoiY"}, {"id": "103", "title": "Redites-moi l'histoire", "url": "https://drive.google.com/uc?export=download&id=1ZS0rAId7K_xIWHLMHO7XCY4ZaaLuQi-i"}, {"id": "104", "title": "Oh! parlez-moi", "url": "https://drive.google.com/uc?export=download&id=1M-ggzxGy_Ge3JIm8RBwRdU_be8o0Gif_"}, {"id": "105", "title": "Sauveur divin", "url": "https://drive.google.com/uc?export=download&id=1hwWkT58p7w7GIyt4U9dDxIJdxYtkoFqn"}, {"id": "107", "title": "Entendez-vous la derni\u00e8re trompette", "url": "https://drive.google.com/uc?export=download&id=1woAYHinNzKxGKZs48T9kn1GNwikbQZ-r"}, {"id": "108", "title": "Il va venir, le Seigneur", "url": "https://drive.google.com/uc?export=download&id=1DwssBVOe5JpvLR97-yQfbdgAtoADv-hD"}, {"id": "109", "title": "Il vient, il vient...", "url": "https://drive.google.com/uc?export=download&id=1lHLSRetGvfIqbxkQ5sx56dehcknAKWtc"}, {"id": "110", "title": "Levons-nous, fr\u00e8res", "url": "https://drive.google.com/uc?export=download&id=1cUWq_ghGnqSNPEC4eHjBbEEf4Jklxu_B"}, {"id": "111", "title": "Il va bient\u00f4t venir!", "url": "https://drive.google.com/uc?export=download&id=1q_2uajhitPK9Z75p0NmtMuTJMR3NARhp"}, {"id": "112", "title": "Du ciel bient\u00f4t, J\u00e9sus va revenir", "url": "https://drive.google.com/uc?export=download&id=1K5KIQb0JEVrrd2xW4xbd0vlqyvE5JXLz"}, {"id": "113", "title": "Il revient sur la nu\u00e9e", "url": "https://drive.google.com/uc?export=download&id=1zRGxra6FnU2k3l-zgKuZQs0JYquM8oSX"}, {"id": "114", "title": "Quel bonheur! J\u00e9sus vient!", "url": "https://drive.google.com/uc?export=download&id=19M4d6hQ41gRdujE7oa1MI4opZWmVj2Cc"}, {"id": "115", "title": "La trompette a retenti", "url": "https://drive.google.com/uc?export=download&id=1lmARcgAPJqZmc4pkc1qER5Fm_-5m_DyF"}, {"id": "116", "title": "Il reviendra!", "url": "https://drive.google.com/uc?export=download&id=1TyFSI6-jltjrsgCwQVx2QjqIV2KJHV-a"}, {"id": "117", "title": "Or, vers minuit...", "url": "https://drive.google.com/uc?export=download&id=1WcuxsQBcCVmVveMPXJrAfwClIcbJkiUr"}, {"id": "118", "title": "Prends courage, chr\u00e9tien", "url": "https://drive.google.com/uc?export=download&id=1hPcLHcEkwwD120kqeqsFV3AroKCapNZz"}, {"id": "119", "title": "Seigneur J\u00e9sus! tes \u00e9lus...", "url": "https://drive.google.com/uc?export=download&id=1yz-iXVxICurcl5nXzVIbCYkhcsoLcydS"}, {"id": "120", "title": "Tenons nos lampes pr\u00eates", "url": "https://drive.google.com/uc?export=download&id=1wA2GxuMaKVCCuub2hs0u2a_NXWh_XKsg"}, {"id": "121", "title": "Ecoutez le chant joyeux", "url": "https://drive.google.com/uc?export=download&id=1bFQlh3irqKCEPL_n0xl5iapRVieFmL0Y"}, {"id": "122", "title": "Esprit du Dieu vivant", "url": "https://drive.google.com/uc?export=download&id=1aKrogs32eJKnL0HjqT6PobMqsi532Hva"}, {"id": "123", "title": "Descends, Esprit du Dieu vivant...", "url": "https://drive.google.com/uc?export=download&id=1xFLaWPp3wbLUffINtD5q55hHwqBJ-v9Z"}, {"id": "124", "title": "R\u00e9ponds \u00e0 ma pri\u00e8re", "url": "https://drive.google.com/uc?export=download&id=1UEJcZkdUOLVUNA6ApN25h0YDKtJlh7Oh"}, {"id": "125", "title": "O Saint-Esprit", "url": "https://drive.google.com/uc?export=download&id=1LwUpNUDBs6O9vwhuQA9YiIxr6_-rFhre"}, {"id": "126", "title": "Don du ciel", "url": "https://drive.google.com/uc?export=download&id=19-A4uF2oytmjrWCDPZMsVNyxu40kfmhW"}, {"id": "127", "title": "Saint-Esprit", "url": "https://drive.google.com/uc?export=download&id=1F1_SNE1iDreFPriRTvfUcJwNusbOuE8f"}, {"id": "128", "title": "Comme une terre alt\u00e9r\u00e9e", "url": "https://drive.google.com/uc?export=download&id=1NnN-7oo8Jdj5B8qoFP5CgIJKIDv4C9-z"}, {"id": "129", "title": "Esprit tr\u00e8s saint", "url": "https://drive.google.com/uc?export=download&id=158Ptw3P8AbdNEU-sfIVBIfLURfaeE31q"}, {"id": "130", "title": "Nous t'adorons, Dieu vivant", "url": "https://drive.google.com/uc?export=download&id=1agvpB06evSCFJvpHv8zEEIc71tdm7Yo6"}, {"id": "131", "title": "Rends-toi ma\u00eetre...", "url": "https://drive.google.com/uc?export=download&id=1RyryGC_Q4kGWeJZneNAV5UMJ9cthq91x"}, {"id": "132", "title": "La Parole du Seigneur", "url": "https://drive.google.com/uc?export=download&id=1NDHpipbotJdKjummV30Lm5XO_DPIvPZ5"}, {"id": "133", "title": "C'est dans ta Parole", "url": "https://drive.google.com/uc?export=download&id=1k-ici5xDnFy9q48HHFRsHBWdVRRkuu6_"}, {"id": "134", "title": "Livre saint", "url": "https://drive.google.com/uc?export=download&id=1QH2E8W8Pb9oNJWMHmMRidoSHb1OPBOWq"}, {"id": "135", "title": "Livre sacr\u00e9, lumi\u00e8re \u00e9tincelante...", "url": "https://drive.google.com/uc?export=download&id=1NQabNZ1AdDX2TZbA2At66TB2vCmf7zl6"}, {"id": "136", "title": "Pour triompher dans les combats", "url": "https://drive.google.com/uc?export=download&id=1xz8O1GWfRhlOT1Qr5rwTGTxCn0DP30k2"}, {"id": "137", "title": "Ta gloire, \u00f4 notre Dieu...", "url": "https://drive.google.com/uc?export=download&id=150Nm0Hc-r8BGmsBgPjFdHQPEuZiza9s-"}, {"id": "138", "title": "Ta Parole, Seigneur", "url": "https://drive.google.com/uc?export=download&id=1aVXNFLHIOiBkJci6KbNtSL52_wahy9l-"}, {"id": "139", "title": "Oh! Que ton joug est facile!", "url": "https://drive.google.com/uc?export=download&id=1gmPwxkruY_A5Z465DIvO38JkILDPBss4"}, {"id": "140", "title": "O Seigneur...", "url": "https://drive.google.com/uc?export=download&id=1YJd7H_wx7ep2geBoPkf3o6cEkezKBMvb"}, {"id": "141", "title": "O Dieu de v\u00e9rit\u00e9", "url": "https://drive.google.com/uc?export=download&id=1QHLn8juip9lDynhc6pLDCSX5SdM82vJR"}, {"id": "142", "title": "L'\u00c9glise est \u00e9trang\u00e8re...", "url": "https://drive.google.com/uc?export=download&id=1a1uDm2-lCZyg7CMwLCAZHEWiSfydDTwS"}, {"id": "143", "title": "C'est moi qui vous console", "url": "https://drive.google.com/uc?export=download&id=1UVfEFoKVGhA45XHN_P5myfXcbi0VGRc0"}, {"id": "144", "title": "Sur ton \u00c9glise universelle", "url": "https://drive.google.com/uc?export=download&id=1V9i53iwQx_irbJGovfzN9vyLz43DCAAX"}, {"id": "145", "title": "Toi qui dans la nuit...", "url": "https://drive.google.com/uc?export=download&id=1onBgwFdqM2khyQFXrviqDtbC2RQuCChm"}, {"id": "146", "title": "Mon \u00e2me, en doux transports", "url": "https://drive.google.com/uc?export=download&id=1WCZ_vdrFGNRf85iTay7SIe9bG3F_5PJH"}, {"id": "147", "title": "Aimer!", "url": "https://drive.google.com/uc?export=download&id=1qxJOe2YI62J5kp84tya5H-806v4Wy5ww"}, {"id": "148", "title": "Ah! Qu'il est beau...", "url": "https://drive.google.com/uc?export=download&id=1nylzKDiZuGyuJFjCD-I2WNGElSSdx5GK"}, {"id": "149", "title": "Fraternit\u00e9 c\u00e9leste et sainte", "url": "https://drive.google.com/uc?export=download&id=1t2s6mkS0ESrfX5BCw_ceOIFqEoXAXT3Q"}, {"id": "150", "title": "Il est en J\u00e9sus-Christ", "url": "https://drive.google.com/uc?export=download&id=1BVxGs6IMM8MR1-4KjEHZO4KGifN1i5Ji"}, {"id": "151", "title": "Nous t'adorons...", "url": "https://drive.google.com/uc?export=download&id=14JQjwsmwCN3977NQ7QxuWlJGP6XS6DL9"}, {"id": "152", "title": "Tu nous aimes, Seigneur!", "url": "https://drive.google.com/uc?export=download&id=1ApJI8Jdt5L-XLiyKoIeW3RPnBAfR_nKD"}, {"id": "154", "title": "L'amour de J\u00e9sus-Christ", "url": "https://drive.google.com/uc?export=download&id=1BDGktl-18hfqWagbLDgywIRAT6gHCnYj"}, {"id": "155", "title": "Ta voix, J\u00e9sus", "url": "https://drive.google.com/uc?export=download&id=1nUI_LKjn4eppWmXsWk-cZBzSFNSvaEgG"}, {"id": "156", "title": "O Seigneur! \u00f4 Sauveur!", "url": "https://drive.google.com/uc?export=download&id=1fcGRg2osgOCeMjU3byyM-S-110SByXAC"}, {"id": "157", "title": "B\u00e9nissons Dieu...", "url": "https://drive.google.com/uc?export=download&id=1p_ddecuYiuqhxF92BjdHSkcJjogT95US"}, {"id": "158", "title": "Devant le Seigneur", "url": "https://drive.google.com/uc?export=download&id=1TKLXJagrW1mi5JxbAtRCQdN-_W7DJuZ8"}, {"id": "159", "title": "Fr\u00e8res, approchons-nous", "url": "https://drive.google.com/uc?export=download&id=1FhY88KxzUL39Z_RsQzU7IR0msqFt9G72"}, {"id": "160", "title": "Marcher en ta pr\u00e9sence...", "url": "https://drive.google.com/uc?export=download&id=1CLcTmMGgz_Td2Aii5bwbzEEco37yNULH"}, {"id": "161", "title": "Immortel Roi des cieux", "url": "https://drive.google.com/uc?export=download&id=181IB5Yx1Yo19QptOxZV3N_a1oG-XbubO"}, {"id": "163", "title": "Silence! Silence!", "url": "https://drive.google.com/uc?export=download&id=13qhgel1uKHxmR5CfZMEXzRVX6eS2loXX"}, {"id": "164", "title": "Jour de repos...", "url": "https://drive.google.com/uc?export=download&id=1b6SZXzXuGClhPB1n08RQiGmrpe4ydGD8"}, {"id": "165", "title": "La semaine a fui", "url": "https://drive.google.com/uc?export=download&id=11nRex2I_GnvDFNuUEhSvBkB9DslBuIt2"}, {"id": "166", "title": "Le jour a fui", "url": "https://drive.google.com/uc?export=download&id=1HrOvkDRtxq4PzdoK4FE67pLGkKRTDaP-"}, {"id": "167", "title": "Monarque souverain", "url": "https://drive.google.com/uc?export=download&id=1FGhxma4GsqJPvaT1qkiZs1QudTwlm29C"}, {"id": "168", "title": "Peuple chr\u00e9tien, c'est le jour...", "url": "https://drive.google.com/uc?export=download&id=1abTQWRovcz3uzBrzj_xKJ1QjSa6DYbDu"}, {"id": "169", "title": "Joyeusement, nous saluons...", "url": "https://drive.google.com/uc?export=download&id=1a_mO_mVs3kc6oTgTk2rYFo5uKnH4_fF0"}, {"id": "170", "title": "Repos si doux", "url": "https://drive.google.com/uc?export=download&id=1c2yjj_4dYSFzTTeRC76uBHR96ARe7CM0"}, {"id": "171", "title": "Quel bonheur, quand faisant tr\u00eave", "url": "https://drive.google.com/uc?export=download&id=15es9OgPHqCDCPb43FgIWkunyeA36FaQh"}, {"id": "172", "title": "Sur la terre se l\u00e8ve...", "url": "https://drive.google.com/uc?export=download&id=1XeKJslDoohHg3IMhhvZ5RY1tLQItas01"}, {"id": "173", "title": "Notre labeur est accompli", "url": "https://drive.google.com/uc?export=download&id=1YXwobQn7Du9KgbpIdeh2UFsuHdNx8Zud"}, {"id": "174", "title": "Ton jour, Seigneur!", "url": "https://drive.google.com/uc?export=download&id=1Tvjt2v0SqmaImPBfBy61DJzurk2YE1mI"}, {"id": "175", "title": "L'astre \u00e0 l'horizon descend", "url": "https://drive.google.com/uc?export=download&id=1wmF3OVljDGIwrC1cOxi06dsDj63Ck1id"}, {"id": "176", "title": "Avec z\u00e8le \u00e0 ton \u00e9cole...", "url": "https://drive.google.com/uc?export=download&id=1shSBP4eSqYKzeV4RpPqZgYGDLcxWxOP0"}, {"id": "177", "title": "Mon \u00e2me en silence", "url": "https://drive.google.com/uc?export=download&id=1qvFSOxLTD24Ee55cwWU7JcznjS4G6MWj"}, {"id": "178", "title": "O Ma\u00eetre supr\u00eame!", "url": "https://drive.google.com/uc?export=download&id=1czyx-w1Xb5t-TbEBYey3AUs_WZxvdb-y"}, {"id": "179", "title": "O ch\u00e8re \u00e9cole du sabbat", "url": "https://drive.google.com/uc?export=download&id=1-kD9jB8SfBy0edwkNN6NUwCR2zE6vDVS"}, {"id": "180", "title": "A tes pieds, \u00f4 divin Ma\u00eetre!", "url": "https://drive.google.com/uc?export=download&id=1ehR-Q0itr0fGBhAR6nD0A_ws3Tx-XuDs"}, {"id": "181", "title": "Repose ton \u00e2me", "url": "https://drive.google.com/uc?export=download&id=1wRUiCqsvq2N1_kDmjF4Y7znNIIr2q5qS"}, {"id": "182", "title": "Parle, parle Seigneur", "url": "https://drive.google.com/uc?export=download&id=1yGRFn2VhLx69eI5PBtS61tOyxrJjTOQa"}, {"id": "183", "title": "Daigne en cette heure...", "url": "https://drive.google.com/uc?export=download&id=1D2f9TNu-fQGX7HjvJYGUpAiiM3L7Okfi"}, {"id": "184", "title": "Divin Sauveur...", "url": "https://drive.google.com/uc?export=download&id=1rOKxfeEHwbyjkvlXVxD-Ay0Rg4wAmBYV"}, {"id": "185", "title": "J\u00e9sus te confie...", "url": "https://drive.google.com/uc?export=download&id=1xnq5sq2VPcW_6GPN2RWi0Qb51KZeZ-n1"}, {"id": "186", "title": "Moment si doux de la pri\u00e8re", "url": "https://drive.google.com/uc?export=download&id=1B5Rx7uCZBM1VZvM6vc30FrXB9eBSNFUa"}, {"id": "187", "title": "O Dieu! toute ma pri\u00e8re", "url": "https://drive.google.com/uc?export=download&id=1fELz4Agr3rCqAQGb6Ed-PbzE6Y9c4gdP"}, {"id": "188", "title": "Seigneur! du sein de la poussi\u00e8re...", "url": "https://drive.google.com/uc?export=download&id=1fSaY0RhSowoTfzxMezokEPe3S4UNZekk"}, {"id": "189", "title": "Quand le ciel devient mena\u00e7ant", "url": "https://drive.google.com/uc?export=download&id=10k9BrDHgnnWS6khez3xFRTpzWeVovUpx"}, {"id": "190", "title": "Toi qui disposes", "url": "https://drive.google.com/uc?export=download&id=1REFmw8_yhiQw-RJZ21BC3GGoMxk0ORk7"}, {"id": "191", "title": "Quelle est douce la pri\u00e8re", "url": "https://drive.google.com/uc?export=download&id=1lDoOJTpYQ9HKRX-yvhX_Cgz2b5Rn2Ota"}, {"id": "192", "title": "Seigneur, ce que je r\u00e9clame", "url": "https://drive.google.com/uc?export=download&id=1cSvu4wL_hJk1YjIZcZJCsoyDBwk8c3Wf"}, {"id": "193", "title": "Souvent Seigneur!", "url": "https://drive.google.com/uc?export=download&id=1mFgupgtcovWhUTfrl0nZiauN3YDHGIgo"}, {"id": "194", "title": "Au sortir de ton sanctuaire", "url": "https://drive.google.com/uc?export=download&id=1tiocs3uZgwnn7tjrDjgj42Yyy2iSYThF"}, {"id": "195", "title": "Demeure par ta gr\u00e2ce", "url": "https://drive.google.com/uc?export=download&id=1nODb_9bXkTaOPmubbPxURxSMP7K6kSkN"}, {"id": "196", "title": "O Seigneur! B\u00e9nis la parole...", "url": "https://drive.google.com/uc?export=download&id=1pPdt4wJrRkptALB37nxWFk5MzQ2jo88n"}, {"id": "197", "title": "Reste avec nous, Seigneur", "url": "https://drive.google.com/uc?export=download&id=1swXCMtIwH971XpIcpTQ3ep6zqJ3hvZSX"}, {"id": "198", "title": "Que l'\u00c9ternel nous b\u00e9nisse...", "url": "https://drive.google.com/uc?export=download&id=1_LUMm5RS86uBuLPQ0pcG17-J7ilzQQfh"}, {"id": "199", "title": "Que la gr\u00e2ce de notre Seigneur...", "url": "https://drive.google.com/uc?export=download&id=1PW0cB0Q5pi6DLSXBCyNs3_RisJrXJDN1"}, {"id": "200", "title": "Dans le vaste champs du monde", "url": "https://drive.google.com/uc?export=download&id=1Ra3wYDd01o7m7DEMPkCUrhHyNBVzGsKO"}, {"id": "201", "title": "La voix de Christ nous appelle", "url": "https://drive.google.com/uc?export=download&id=1kfbYJbcYUsMqqtMTNjMv_eUTkiLDKWsf"}, {"id": "202", "title": "Passez jusques \u00e0 nous!", "url": "https://drive.google.com/uc?export=download&id=1Yy6UeOBSP7KrLCG_BCJrp4-JQk6186Bf"}, {"id": "203", "title": "Fr\u00e8res, chantons...", "url": "https://drive.google.com/uc?export=download&id=1czkcBKe20PgFmfNxE82gx5MoybOiUk74"}, {"id": "204", "title": "Des pays de l'aurore...", "url": "https://drive.google.com/uc?export=download&id=1lL76Xp8sPiLSglaedjWeyZpWoOzIKdl6"}, {"id": "205", "title": "Oui, la moisson du monde...", "url": "https://drive.google.com/uc?export=download&id=1PHI2MQgsU-8-j7CkghqQoEhDz-BoDhQS"}, {"id": "206", "title": "L\u00e8ve-toi, vaillante arm\u00e9e", "url": "https://drive.google.com/uc?export=download&id=1tSvGIP57G2bQtslIOHfTksYvbz4ZRbhM"}, {"id": "207", "title": "Qu'ils sont beaux...", "url": "https://drive.google.com/uc?export=download&id=1hLfIc2ZfhdvTbIMK2AEeL9znhkJBzrDj"}, {"id": "208", "title": "Semons d\u00e8s que brille l'aurore", "url": "https://drive.google.com/uc?export=download&id=1743a2XTnrVjKb4YpNQiIQu0L9b-_D7Q-"}, {"id": "209", "title": "Soleil de justice", "url": "https://drive.google.com/uc?export=download&id=14kTHpwxai6rZQxbp1G7CToyjEOaNzTvJ"}, {"id": "210", "title": "Seigneur J\u00e9sus!", "url": "https://drive.google.com/uc?export=download&id=1N3T6C5M997vJoRgw9FVV9AVPgBgrVlre"}, {"id": "211", "title": "Viens, \u00f4 J\u00e9sus! r\u00e9gner...", "url": "https://drive.google.com/uc?export=download&id=1k5tOb4ZsgFvb2tGuIKMTK0h7WWC7l_3e"}, {"id": "212", "title": "Annon\u00e7ons partout...", "url": "https://drive.google.com/uc?export=download&id=1AG43WecmqwSxY-xEJITP394ehiPnn0L-"}, {"id": "213", "title": "Cloches, sonnez l'\u00c9vangile", "url": "https://drive.google.com/uc?export=download&id=1pvRw_ioMrEDxpYruexpVIWjxU5F5D1BE"}, {"id": "214", "title": "Chantons la victoire", "url": "https://drive.google.com/uc?export=download&id=1XDTGW_Ht3L0qf1W5cv8z7YNj3LHjiqUj"}, {"id": "215", "title": "Entends-tu le chant joyeux?", "url": "https://drive.google.com/uc?export=download&id=1HqpJEYEURrreT6TX5SqAP7Yv2ngakdYn"}, {"id": "216", "title": "Seigneur, ton ange vole", "url": "https://drive.google.com/uc?export=download&id=1pNmZEq9MEqbenw2IY3IfqmgHcq2GYZZN"}, {"id": "217", "title": "R\u00e9jouis-toi, chr\u00e9tien...", "url": "https://drive.google.com/uc?export=download&id=1Wb3IX2oNwegVjrJQgq5xirzqOIIYEAPy"}, {"id": "218", "title": "Tel que je suis", "url": "https://drive.google.com/uc?export=download&id=1xvRhN5DswvhR71Gal97XXRoHWXGxErss"}, {"id": "219", "title": "Contemplez, \u00f4 chr\u00e9tiens!", "url": "https://drive.google.com/uc?export=download&id=1kzdj43-YDMvIZTvO0cM96wsaVjvmkbbA"}, {"id": "220", "title": "Je viens, Seigneur.", "url": "https://drive.google.com/uc?export=download&id=13ShWk_-g8cXpcULBsNHgV5gvgQfvWxIo"}, {"id": "221", "title": "De ce monde...", "url": "https://drive.google.com/uc?export=download&id=1nTtBSMiIVOpK83XhNK-lpoAy9hc0gSF5"}, {"id": "222", "title": "Mort avec Christ", "url": "https://drive.google.com/uc?export=download&id=1CrDnbNsN3tSMw2RfGnDxLUzxxvbjMPh8"}, {"id": "223", "title": "Seigneur J\u00e9sus...", "url": "https://drive.google.com/uc?export=download&id=1lSuLcvVwoFDM5YhY3fgMWzym6s5_jLwP"}, {"id": "224", "title": "Tel que je suis sans rien \u00e0 moi", "url": "https://drive.google.com/uc?export=download&id=1gfUDjI5g_rNNrwYcVMckYbn2bT3WMPeY"}, {"id": "225", "title": "Viens \u00e0 la croix", "url": "https://drive.google.com/uc?export=download&id=1XqUaN2rjVhMd3AWNzfdHSbpxKbp2pKTo"}, {"id": "226", "title": "C\u00e9leste voix, tu nous convies", "url": "https://drive.google.com/uc?export=download&id=1voigkpYLXbtXHuLFzUgzXR88q1i0V94u"}, {"id": "227", "title": "Agneau, victime expiatoire", "url": "https://drive.google.com/uc?export=download&id=1GqonVEMvZUqPzD4wIl5LHQHUKozbqZnM"}, {"id": "228", "title": "A ta C\u00e8ne b\u00e9nie", "url": "https://drive.google.com/uc?export=download&id=10ccZy13xCI6XvHQP9oX8CTsXtDG1VcH-"}, {"id": "229", "title": "Je viens, Seigneur, \u00e0 ta table b\u00e9nie...", "url": "https://drive.google.com/uc?export=download&id=1O9UbiLjOGGZW0t3El5_cyiN2JZBpf0La"}, {"id": "230", "title": "Roi des rois, victime sainte...", "url": "https://drive.google.com/uc?export=download&id=1f73KBhRDBF5T1Hm0K9yCF-IfXU1vu6kL"}, {"id": "231", "title": "Tu m'appelles, Seigneur", "url": "https://drive.google.com/uc?export=download&id=1f46gwQ8hIlwOraVrHq5WTYZ-dxwwiKKq"}, {"id": "232", "title": "Bient\u00f4t le Seigneur va venir!", "url": "https://drive.google.com/uc?export=download&id=1bh0lpBCK4xVp2In8M07QXReMnrEEgkOW"}, {"id": "233", "title": "C'est encor temps", "url": "https://drive.google.com/uc?export=download&id=1ZeXZCDBEJm_ZPjcKW6MfasL7BrdFa6bP"}, {"id": "234", "title": "J\u00e9sus frappe \u00e0 votre porte", "url": "https://drive.google.com/uc?export=download&id=1VezqCsfDHyHO8s3bT_x9VJPHgP5sNTVw"}, {"id": "235", "title": "Arr\u00eate, \u00f4 p\u00e9cheur", "url": "https://drive.google.com/uc?export=download&id=1cyjAppE_IlqdA-SDvalm31OE-bimZtYn"}, {"id": "236", "title": "Entends-tu? J\u00e9sus t'appelle", "url": "https://drive.google.com/uc?export=download&id=15GD6unNvTxTwtEdwbyJzoX76YpwZ92U6"}, {"id": "237", "title": "Pour toi, j'ai donn\u00e9 ma vie...", "url": "https://drive.google.com/uc?export=download&id=1U9eITAEdN64ll-6dFQbEgh-TI2ASH_u3"}, {"id": "238", "title": "Regarde, \u00e2me angoiss\u00e9e", "url": "https://drive.google.com/uc?export=download&id=1nU6SFIonfrxka3HpbJLbBr2mRfuPPcci"}, {"id": "239", "title": "Lorsque devant l'agneau...", "url": "https://drive.google.com/uc?export=download&id=1d1mFHX6wtMiW5aPDHeD2WajUC_EIfRNg"}, {"id": "240", "title": "Nous voguons vers un beau rivage", "url": "https://drive.google.com/uc?export=download&id=1FtGKM2Ib3qBkd2r-FhBN8zUjDxJniutL"}, {"id": "241", "title": "Viens, \u00e2me perdue", "url": "https://drive.google.com/uc?export=download&id=1facXi6dBjlVYWa_E2oidoORdv0pAAIhT"}, {"id": "242", "title": "Le Ma\u00eetre est l\u00e0 qui t'appelle", "url": "https://drive.google.com/uc?export=download&id=1Kr8LaM2hXk_bwDZUacrshZHZkEUrD1Xl"}, {"id": "243", "title": "O vous qui n'avez pas la paix", "url": "https://drive.google.com/uc?export=download&id=16CnpjQJSF0CKk1wfaeXZ5l0hZ7SBT8df"}, {"id": "245", "title": "Veux-tu partager la gloire", "url": "https://drive.google.com/uc?export=download&id=192tNYz_cbkQc1K1WcrHmPOBn8Z3wK8HK"}, {"id": "246", "title": "Passant, si tard que veux-tu?", "url": "https://drive.google.com/uc?export=download&id=1ZYlfSRb_wmvo3j7ZThAG69bn61QpMExl"}, {"id": "247", "title": "Reviens \u00e0 ton P\u00e8re...", "url": "https://drive.google.com/uc?export=download&id=1ZUzoJcgU5PHZV5nZDDMaHXI4ssPuy9hC"}, {"id": "249", "title": "P\u00e9cheur, je voudrais te gu\u00e9rir", "url": "https://drive.google.com/uc?export=download&id=14ze9Is_JkK-leoWgXzytt4JdbBDW6XwW"}, {"id": "250", "title": "Poss\u00e8des-tu, pauvre p\u00e9cheur", "url": "https://drive.google.com/uc?export=download&id=1t4FVPEXs7DL_hQr2WqhTPKGRrY-WzwNH"}, {"id": "251", "title": "Pour nous la vie est un voyage", "url": "https://drive.google.com/uc?export=download&id=1aa3nWxkecmzo8dPdUeZ5JsgGQhoAdsqk"}, {"id": "252", "title": "Viens \u00e0 J\u00e9sus", "url": "https://drive.google.com/uc?export=download&id=1oPwO5PptQQQzmhi5WIvKmbEDLkEBzqJo"}, {"id": "253", "title": "Reviens!", "url": "https://drive.google.com/uc?export=download&id=1-MX3mO5Qe-nSGYi4d1t7bK_-fH5nmARB"}, {"id": "254", "title": "Une bonne nouvelle", "url": "https://drive.google.com/uc?export=download&id=16OOWMtvnNGbiYmokxjiCsIRbPD-p-rXX"}, {"id": "255", "title": "Si vous saviez...", "url": "https://drive.google.com/uc?export=download&id=17c0yjkYKKhxNhOWSj7q2J0d6SOJqK4Wl"}, {"id": "256", "title": "Toi dont l'\u00e2me est tourment\u00e9e", "url": "https://drive.google.com/uc?export=download&id=1qCtYrgx1tEJuzYOWTqHNMuaJXaOU_0zH"}, {"id": "257", "title": "Venez au Sauveur", "url": "https://drive.google.com/uc?export=download&id=1nrxYvWbkVpPs0kO7C3mBdgfQGvXj5IQG"}, {"id": "258", "title": "Viens \u00e0 J\u00e9sus, quand la souffrance...", "url": "https://drive.google.com/uc?export=download&id=1RK_BD6TGIaN2MvnNq2-Gn33b1XgUCXCT"}, {"id": "259", "title": "Viens au P\u00e8re", "url": "https://drive.google.com/uc?export=download&id=1uvMvFtsSC9oMhbrazTZW05ssl1DgBfli"}, {"id": "260", "title": "Voici J\u00e9sus, notre Sauveur", "url": "https://drive.google.com/uc?export=download&id=1jsaH2ewVqFhpfVxA01TG5QH6kAUeWkd3"}, {"id": "261", "title": "Nous allons tout joyeux...", "url": "https://drive.google.com/uc?export=download&id=1pRyB_HhxaB8HVdAKkfE75uIMhlAVHkzb"}, {"id": "262", "title": "A ton appel, sur les flots", "url": "https://drive.google.com/uc?export=download&id=1nrcVB9nJBmjdXDHZgeRoQWUIDwkYx4Wj"}, {"id": "263", "title": "Aujourd'hui tu m'appelles", "url": "https://drive.google.com/uc?export=download&id=1Go6N8BpUsC2QcQDYSVUf3xkUeuBrnzQo"}, {"id": "264", "title": "Chantez, anges du ciel!", "url": "https://drive.google.com/uc?export=download&id=19xJvVVAUejd7xYetWb4Fisg3xeLrYM92"}, {"id": "266", "title": "O Seigneur", "url": "https://drive.google.com/uc?export=download&id=1zKxbcTuqrri5BaSR9Z7Yk42WAmpleCg2"}, {"id": "267", "title": "Seigneur, tu donnes ta gr\u00e2ce", "url": "https://drive.google.com/uc?export=download&id=16rhN8xdLLHdlTmsqOJtaM3rI5WToq7Af"}, {"id": "268", "title": "J\u00e9sus, par ton sang pr\u00e9cieux", "url": "https://drive.google.com/uc?export=download&id=1U7ZvZnFDzDimLh9CBgWmyYqazvGc3s2d"}, {"id": "269", "title": "O Fils de Dieu, mon Sauveur", "url": "https://drive.google.com/uc?export=download&id=1DAnDVSJ41tRzsOqSyOW9a_ibHWI5-DRU"}, {"id": "270", "title": "J'ai trouv\u00e9 la voie", "url": "https://drive.google.com/uc?export=download&id=1fXeilKV-en5rynvnoVawPGZAHGwSJXU8"}, {"id": "271", "title": "Mis\u00e9ricorde insondable", "url": "https://drive.google.com/uc?export=download&id=1BGEdvAmztY_Z_oyR83M7g-Tdlcvgw-67"}, {"id": "274", "title": "Source f\u00e9conde", "url": "https://drive.google.com/uc?export=download&id=133YSBFYmX7Nr6qThZu_m60yMBqF_zw4C"}, {"id": "275", "title": "J'avais fui la bergerie", "url": "https://drive.google.com/uc?export=download&id=1SaWq2-FrhpHqSg9X7OggDIOuzudAlxLB"}, {"id": "276", "title": "Bien loin de toi, mon P\u00e8re", "url": "https://drive.google.com/uc?export=download&id=1sL53gl1nLA7CPqpA0mWFC-MgSjwGmy3i"}, {"id": "277", "title": "J'ai longtemps err\u00e9...", "url": "https://drive.google.com/uc?export=download&id=1QADmXtr9QtBZbqiWm-5ubN57NQtPtYBI"}, {"id": "278", "title": "Me voici devant ta face", "url": "https://drive.google.com/uc?export=download&id=1nNlf21lMUlSANda5EOlbTmH95pf6V1G_"}, {"id": "279", "title": "O honte! \u00f4 m\u00e9moire cruelle!", "url": "https://drive.google.com/uc?export=download&id=1K15gOAZil6qmfxYWUwb14rilkroJn_MH"}, {"id": "280", "title": "P\u00e8re, je viens \u00e0 toi", "url": "https://drive.google.com/uc?export=download&id=1kTTkl3uHyLiv44irxZLPOmTpNJbqc-63"}, {"id": "282", "title": "Roc s\u00e9culaire", "url": "https://drive.google.com/uc?export=download&id=1W1h--NgVGWZHoenBRAE7K9qeAmTn6sP6"}, {"id": "283", "title": "Sans attendre", "url": "https://drive.google.com/uc?export=download&id=1ZmhbhsqZ4YIpen5qiZvN8EV4pAsygbKb"}, {"id": "284", "title": "Seigneur, attire...", "url": "https://drive.google.com/uc?export=download&id=1NvyVRBafSW02bDMcNg_GTLUaJXSFiGrC"}, {"id": "285", "title": "C'est toi, J\u00e9sus", "url": "https://drive.google.com/uc?export=download&id=1MsMEBbBRiryYCBVutLWardN744JzagnC"}, {"id": "286", "title": "Il est un nom si beau", "url": "https://drive.google.com/uc?export=download&id=1qhgQAbCkbTsi5IUFXG839muTxqbmiNCS"}, {"id": "287", "title": "Exaltons notre divin Ma\u00eetre", "url": "https://drive.google.com/uc?export=download&id=1owbnB6eFKssC4c5U48u1us4dQa-BWTHM"}, {"id": "288", "title": "En quelque lieu...", "url": "https://drive.google.com/uc?export=download&id=1h6Q8hbVD94bId7ctpYrpoCfy4GSTc2PN"}, {"id": "289", "title": "Roi des anges", "url": "https://drive.google.com/uc?export=download&id=1cXUpJ43AZHmnmgR9V_2QcpKoeHbDX00p"}, {"id": "291", "title": "Je connais un guide...", "url": "https://drive.google.com/uc?export=download&id=1jzsM3Ey1qdKeuUYIPpvDckMpybJu6_5k"}, {"id": "294", "title": "Dou\u00e9 du langage des anges...", "url": "https://drive.google.com/uc?export=download&id=1DBZr7IjibIjqIxveOO7mK_JcjYUQ0Lym"}, {"id": "295", "title": "Je dois voyager...", "url": "https://drive.google.com/uc?export=download&id=1RWrPY5NgYYzA_PXedxEHLgruXN1HSJCV"}, {"id": "296", "title": "Quel autre au ciel...", "url": "https://drive.google.com/uc?export=download&id=1MVl9MZTPTXCzLVD4q5W55dtihBi24H7l"}, {"id": "297", "title": "T'aimer, J\u00e9sus, te conna\u00eetre...", "url": "https://drive.google.com/uc?export=download&id=1NXb_Vhjnhtf8c3LgVxhOWSFnCixFLBpn"}, {"id": "299", "title": "Jour apr\u00e8s jour", "url": "https://drive.google.com/uc?export=download&id=1y1WK_tphWsQw-PcGEgxJs5__ENT5fVEY"}, {"id": "300", "title": "Vaillants soldats...", "url": "https://drive.google.com/uc?export=download&id=1vcA6y9IYotLAHeNH_3U-aeWYid3RXrcr"}, {"id": "301", "title": "La foi", "url": "https://drive.google.com/uc?export=download&id=1G9DI68NixGAWw7VXriKN-_PIqaMEtzmx"}, {"id": "302", "title": "Le Dieu saint", "url": "https://drive.google.com/uc?export=download&id=1uYgUEVi2PhDOQswQ0LtD_i4bTPFKxnA-"}, {"id": "304", "title": "Brillante \u00c9toile", "url": "https://drive.google.com/uc?export=download&id=1n7F8XX5UVLQdeUsaJ7hOQJF0diYmu2ZB"}, {"id": "305", "title": "Ami, pourquoi tant de bonheur", "url": "https://drive.google.com/uc?export=download&id=1Fj3E9BybvshG7fWcm-9fH3ptObvVlU-q"}, {"id": "306", "title": "Comme un fleuve immense", "url": "https://drive.google.com/uc?export=download&id=14gCOCM3l5oH87bVBfnkm9NlFurd_uiVI"}, {"id": "307", "title": "En toi, Seigneur", "url": "https://drive.google.com/uc?export=download&id=1CCP3R00nU4Tk0HW27g1fn2WiqxiOg255"}, {"id": "308", "title": "Eternel Dieu, mon Sauveur", "url": "https://drive.google.com/uc?export=download&id=10Y8WHuVwY6kSKfHAeao9wc74AZIBlOZ7"}, {"id": "309", "title": "La Croix que Dieu me donne", "url": "https://drive.google.com/uc?export=download&id=1xR2nscOU8b5N3GwzITQnwDkf1qXAUcmN"}, {"id": "310", "title": "Mon bonheur vient de toi", "url": "https://drive.google.com/uc?export=download&id=1CPFbBnGNSwIE5dQNXAAhs6idylEp-c6O"}, {"id": "311", "title": "J'ai soif de paix", "url": "https://drive.google.com/uc?export=download&id=1KL67NC5Fk1h6DHJ8pVKUB9-zwr_Iknvx"}, {"id": "313", "title": "Mon Dieu, nos coeurs...", "url": "https://drive.google.com/uc?export=download&id=1ScDf5Xwv8Dw4RMKP9SMLusIfLP9g55we"}, {"id": "314", "title": "Quand le ciel s'ouvre...", "url": " https://drive.google.com/uc?export=download&id=1UgRIUue06S_EmgOTLoGrDIs86Fz_-8NX"}, {"id": "315", "title": "Sauveur toujours fid\u00e8le...", "url": "https://drive.google.com/uc?export=download&id=1IANXFEoB4Bg2m30Ga37pe0G6jM8vR_9a"}, {"id": "316", "title": "Mon coeur joyeux", "url": "https://drive.google.com/uc?export=download&id=1xQzfxK3TJQk882kCYU_pLJUDbhh6TzxO"}, {"id": "317", "title": "Oh! quel repos, quand le mal...", "url": "https://drive.google.com/uc?export=download&id=1U7k_VYyJfgwR9Tsra8GEvccpTgyjGwby"}, {"id": "318", "title": "Plus le mal est pressant...", "url": "https://drive.google.com/uc?export=download&id=1FFcOW564CzQ1pCZ6EAeUIPoqavth_vgJ"}, {"id": "319", "title": "Pr\u00e8s de J\u00e9sus", "url": "https://drive.google.com/uc?export=download&id=1myv5GWIglXbzUjb3Wie5HFiqrgi_58Jy"}, {"id": "320", "title": "Quel ami fid\u00e8le et tendre!", "url": "https://drive.google.com/uc?export=download&id=1E99DxgMotVY-BKXyK4Ow5_WkjdQbaY04"}, {"id": "322", "title": "Seul refuge de mon \u00e2me", "url": "https://drive.google.com/uc?export=download&id=16i36CCYz3-e5594S5adxsfbblgMLZpKl"}, {"id": "323", "title": "Source de tous les biens", "url": "https://drive.google.com/uc?export=download&id=107EoSxqoGdQR5LHyBqrtkSQMJ8duy_hJ"}, {"id": "324", "title": "Sur toi, je me repose...", "url": "https://drive.google.com/uc?export=download&id=1J8GSQSSUX39Tl9fh1zNH2-MtuXbygXZS"}, {"id": "325", "title": "A J\u00e9sus, je m'abandonne...", "url": "https://drive.google.com/uc?export=download&id=1rYiey4tc_HwFpSpelJv3-nr74lzaKdvq"}, {"id": "326", "title": "Ah! Donne \u00e0 mon \u00e2me", "url": "https://drive.google.com/uc?export=download&id=1bmI5GIs-wj6fsRjlSDCM-2eIBoY6MsIV"}, {"id": "327", "title": "Grandis en moi, Seigneur", "url": "https://drive.google.com/uc?export=download&id=1RQR5PLiCM9jqyDGMZBGKmcAYDoFQd3fx"}, {"id": "328", "title": "Je me tiendrai tout pr\u00e8s...", "url": "https://drive.google.com/uc?export=download&id=1toawv4IEsXTE_zZWcDnKqLD05NQr3uey"}, {"id": "329", "title": "Ah! que je ne sois pas...", "url": "https://drive.google.com/uc?export=download&id=1TiOPwJeIUAp8fQ2Q91hFlVDvjMRwqrp2"}, {"id": "333", "title": "Seigneur, sanctifie", "url": "https://drive.google.com/uc?export=download&id=1hjT_VRMct0h8ur67eIZKh5yFaLexY46N"}, {"id": "334", "title": "C'est mon joyeux service...", "url": "https://drive.google.com/uc?export=download&id=1SFjd9g1JSigVH_T4R0deEXOgaLXLzMvj"}, {"id": "335", "title": "Le cri de mon \u00e2me", "url": "https://drive.google.com/uc?export=download&id=1gBexERW07CsncaWknJ6B9JLJ5T7UBBaR"}, {"id": "336", "title": "J\u00e9sus-Christ est ma sagesse", "url": "https://drive.google.com/uc?export=download&id=1sdPB-qPRyr7Aktavz5aqVfeSm_KSD7bR"}, {"id": "338", "title": "Les gains, les honneurs...", "url": "https://drive.google.com/uc?export=download&id=1VLa4vjP9AA6xJY5GSo4vYq9OH_fyN4nm"}, {"id": "339", "title": "Mon Sauveur", "url": "https://drive.google.com/uc?export=download&id=1ibzh_0L6TnQd0ru1sgVQvHM6C2Hfa94j"}, {"id": "341", "title": "O mon Sauveur!", "url": "https://drive.google.com/uc?export=download&id=1i6ZyyIj-TRgEQL3d-yhiwgitSbghsajt"}, {"id": "342", "title": "Qu'il fait bon \u00e0 ton service", "url": "https://drive.google.com/uc?export=download&id=18BiF0br-oEj-oBSsau-ULs3ua9CnCrjP"}, {"id": "343", "title": "Toujours avec J\u00e9sus!", "url": "https://drive.google.com/uc?export=download&id=17Q0AzTbdOj8xjfbz65mx7Cmoqslht4VR"}, {"id": "344", "title": "A moi, les coeurs braves!", "url": "https://drive.google.com/uc?export=download&id=1MZ8ubYzx6Sg4ESA3yADtWPWgoahcQIdD"}, {"id": "345", "title": "Plus que vainqueurs!", "url": "https://drive.google.com/uc?export=download&id=12eHNcsV2Ak9VQ0FpABGvFcLL7IO-FIDs"}, {"id": "346", "title": "A de nouveaux combats", "url": "https://drive.google.com/uc?export=download&id=19iiOj-uR5KmGWumRqWiOaoCvEEPXZohr"}, {"id": "347", "title": "Debout, sainte cohorte", "url": "https://drive.google.com/uc?export=download&id=1oORJP3Ndih0LetECT1lnPls4btWwIEdA"}, {"id": "348", "title": "D\u00e8s que l'aube d\u00e9pose.", "url": "https://drive.google.com/uc?export=download&id=1ljQ8b5R8huCzqabMqa8j4hpSUE2Hpo8q"}, {"id": "349", "title": "D\u00e8s que l'aube d\u00e9pose", "url": "https://drive.google.com/uc?export=download&id=1IUs6zhbTdq49VGuDXmSouCqgmZ2IeP_i"}, {"id": "350", "title": "Seigneur dirige tous mes pas...", "url": "https://drive.google.com/uc?export=download&id=14RK-1RaC7gORLKKi-2yTqRegCAWnBuwK"}, {"id": "351", "title": "Debout! soldats du Christ", "url": "https://drive.google.com/uc?export=download&id=14UjUsDyCrs6JBHbgf115bUiEjJMof9Xf"}, {"id": "352", "title": "Jusqu'\u00e0 la mort!", "url": "https://drive.google.com/uc?export=download&id=1F_z1Z92RBPgPkvv0Td48D-v3cWZeQsdJ"}, {"id": "353", "title": "Le temps est court", "url": "https://drive.google.com/uc?export=download&id=1Xe6k1PMpvESjrURaJLld4QOntnK04TKB"}, {"id": "355", "title": "L'heure du d\u00e9part", "url": " https://drive.google.com/uc?export=download&id=1l4mga5SKEZxVBfpLbRKl6YpGFtNJpUeu"}, {"id": "356", "title": "Mon Dieu! quelle guerre cruelle!", "url": "https://drive.google.com/uc?export=download&id=1qsjjN917GlkI6wtiAcCouUxzNakki9M6"}, {"id": "357", "title": "Poursuivons notre course", "url": "https://drive.google.com/uc?export=download&id=1gw7noi0s0xqfleaYqlSixmMAwCzTrxrv"}, {"id": "358", "title": "C'est un rempart", "url": "https://drive.google.com/uc?export=download&id=1oQese8YHHyudw-Rb0ZeRaNqWXeWZbA5q"}, {"id": "359", "title": "J'ai soif de ta pr\u00e9sence", "url": "https://drive.google.com/uc?export=download&id=1UxssaVl3TaPssW7q-K1VlLtDFTh8wREd"}, {"id": "365", "title": "Trop souvent, je murmure...", "url": "https://drive.google.com/uc?export=download&id=1Q8G36-e_JPoYL-J8vV_0c3f_wDNA4Xwg"}, {"id": "366", "title": "Veille au matin", "url": "https://drive.google.com/uc?export=download&id=1R-Yxap2WcZMoqB3gLe2J7yu7ivpbvY_4"}, {"id": "367", "title": "Dans le d\u00e9sert...", "url": " https://drive.google.com/uc?export=download&id=1WBSccU2E3NTvHcfAP3Vpp8OmVBgW7nXo"}, {"id": "368", "title": "Mon Dieu, plus pr\u00e8s de toi.", "url": "https://drive.google.com/uc?export=download&id=1ea9JXSTJOa78cU53MPLs1_ehQuAUa_gq"}, {"id": "369", "title": "En ce triste monde...", "url": "https://drive.google.com/uc?export=download&id=1F5sF5jLe2qOROGZyK_MVQbPV3fr2RKB_"}, {"id": "371", "title": "Il est une source", "url": "https://drive.google.com/uc?export=download&id=1H5urFodKmQC4G9LejcFej2dMEsutXOzb"}, {"id": "373", "title": "J\u00e9sus est celui qui nous aime", "url": "https://drive.google.com/uc?export=download&id=1o-qvgjLdw7knot2mdWvGWRsOIQJ-Lm0j"}, {"id": "374", "title": "Le ciel \u00e9tait voil\u00e9", "url": "https://drive.google.com/uc?export=download&id=10BQjtjrRzKCB29S9v8o61ScQYa0KDleV"}, {"id": "375", "title": "Ma\u00eetre, entends-tu la temp\u00eate?", "url": "https://drive.google.com/uc?export=download&id=1922hj2IQ48ldPRQkncPegJ4YTjsoJO2P"}, {"id": "376", "title": "Le vent soufflait...", "url": "https://drive.google.com/uc?export=download&id=1TCqVHkHD75l5sORzCqRxvv15PTITqSs8"}, {"id": "377", "title": "Mon \u00e2me est dans la d\u00e9tresse", "url": "https://drive.google.com/uc?export=download&id=1B-4TPz9fudXI89YOhQNBaFgHOTMuRtrF"}, {"id": "378", "title": "O J\u00e9sus, mon Sauveur", "url": "https://drive.google.com/uc?export=download&id=1tbg09cOoM-e5N7S_11yYbOBNLpH6uH7c"}, {"id": "379", "title": "O jour b\u00e9ni!", "url": "https://drive.google.com/uc?export=download&id=1bRuoujRvd8O1fCoOZaNpSmsB9x4R6FpR"}, {"id": "380", "title": "O toi, mon all\u00e9gresse", "url": "https://drive.google.com/uc?export=download&id=13rU9jwkqMvXBDhS-6IPzfpa2Dq83n6tb"}, {"id": "381", "title": "O\u00f9 trouver une retraite", "url": "https://drive.google.com/uc?export=download&id=1mERLTML3g5zRNRJM6UK6O8C-aE92NZup"}, {"id": "383", "title": "Quel grand secours!", "url": "https://drive.google.com/uc?export=download&id=1mGHqGmpgTtUMDoc7ZX3KzoqqbFA7GUmr"}, {"id": "385", "title": "Quand sur la sombre route", "url": "https://drive.google.com/uc?export=download&id=1JrknVrkw6qFh479uelw_mqVKX981O2hy"}, {"id": "386", "title": "Qui me rel\u00e8ve...", "url": "https://drive.google.com/uc?export=download&id=1-TclhX2lXiRo0_2jxizKVwesozMkxBy0"}, {"id": "387", "title": "Si je trouve grande ma croix", "url": "https://drive.google.com/uc?export=download&id=1Fxl96QIcQ4ukVy_diHHrVhtS7upy-V9T"}, {"id": "388", "title": "Une nacelle en silence", "url": "https://drive.google.com/uc?export=download&id=1t9BgaE1zyfznGjFWQmWXtZSKmwRP8tQF"}, {"id": "389", "title": "C\u00e9leste Canaan", "url": "https://drive.google.com/uc?export=download&id=171Dn_RDUFaufBkyzG8NVB8XhAKhcQhPM"}, {"id": "390", "title": "Au ciel est la maison du P\u00e8re", "url": "https://drive.google.com/uc?export=download&id=1bbPZoR9QMgnjBlmsLUFWO_o6vg8AGVoS"}, {"id": "391", "title": "Avec all\u00e9gresse!", "url": "https://drive.google.com/uc?export=download&id=1VDSv5GsBHtaF_69JY5XNXKb_eS013NUP"}, {"id": "392", "title": "De Canaan, quand verrons-nous", "url": "https://drive.google.com/uc?export=download&id=1veuoEtOgO_ZYNxp21HWjl9xROhWE5sq5"}, {"id": "393", "title": "Vers le ciel", "url": "https://drive.google.com/uc?export=download&id=1XIrC7C_7-suwl7x1fA5o6WPb3-FheEuW"}, {"id": "394", "title": "Contempler mon Dieu", "url": "https://drive.google.com/uc?export=download&id=1Mtml-JHSoyS8tq2Kn3yrc-2rlrpaPXw4"}, {"id": "395", "title": "Encor quelques jours sur la terre", "url": "https://drive.google.com/uc?export=download&id=1RroggKSpIjsdnIuHZBLv2b0vk96xCZ1G"}, {"id": "396", "title": "Sainte Sion", "url": "https://drive.google.com/uc?export=download&id=1wvGe5yb8Zx9vnOh2OBh1Hk84vrxRCnUu"}, {"id": "397", "title": "Etranger sur la terre", "url": "https://drive.google.com/uc?export=download&id=13ytgHBzCtl11LDajfn8WkFZCpaAIGjel"}, {"id": "399", "title": "Je connais un pays...", "url": "https://drive.google.com/uc?export=download&id=1ydzm1gxCoTMeTeGpe0dZqlCsRfO16Fj3"}, {"id": "402", "title": "L'aube na\u00eet, sourit et passe", "url": "https://drive.google.com/uc?export=download&id=1apzhdjPhh3g6AxZjzWfLaR27f4eXY4go"}, {"id": "404", "title": "Matelots en voyage", "url": "https://drive.google.com/uc?export=download&id=1AENyZco5tRLHHtI0FPcQvV1qm4wzObal"}, {"id": "405", "title": "Monts et coteaux reverdissent", "url": "https://drive.google.com/uc?export=download&id=10No7jRecqEzMG7LKoGkXv3oKxw5EcW8R"}, {"id": "406", "title": "Nous attendons le Sauveur glorieux!", "url": "https://drive.google.com/uc?export=download&id=10B-0bIF8clXnOxP9qdlbxUd6WdtTx72p"}, {"id": "407", "title": "P\u00e8lerin sur cette terre", "url": "https://drive.google.com/uc?export=download&id=1q9aahICDzOdi1q3IvZDdCZ2A4sPWnJMs"}, {"id": "408", "title": "Plus haut que les hautes cimes", "url": "https://drive.google.com/uc?export=download&id=1wl1XISl5730zocMHGo_7mUNcynJl6mFQ"}, {"id": "410", "title": "Qui sont ces gens ...", "url": "https://drive.google.com/uc?export=download&id=1gRjJernnwxCBzpsv6eeHU3isWqpRcf-a"}, {"id": "411", "title": "Que ta lumi\u00e8re...", "url": "https://drive.google.com/uc?export=download&id=1MLpvuhvsbjanP4_V_MQc1XxYD38kOM-4"}, {"id": "412", "title": "D\u00e8s le matin, Seigneur", "url": "https://drive.google.com/uc?export=download&id=1pnekXdrMmdtHdfBD53BCPU0sWzbbeqGG"}, {"id": "413", "title": "O mon Dieu! Je cherche ta face", "url": "https://drive.google.com/uc?export=download&id=1CavD-thpFHXMLaZRYsfWEl19qkB6SuO_"}, {"id": "414", "title": "Pour moi l'aurore...", "url": "https://drive.google.com/uc?export=download&id=15fQsnm9duu20ZpF_zvd-RzcsKdyFOALL"}, {"id": "415", "title": "Une voix dans mon coeur...", "url": "https://drive.google.com/uc?export=download&id=13BpoF1ozwqcOej9O2sFbToAbx0wP5vYF"}, {"id": "416", "title": "Je viens, Seigneur", "url": "https://drive.google.com/uc?export=download&id=1KqWSaPM0ZyNkmT3X2RfoRcavwf8eHXb7"}, {"id": "417", "title": "J'aime l'heure o\u00f9 sur la terre...", "url": "https://drive.google.com/uc?export=download&id=1mVLfG-AXgy08dkckFrx_-adtmtcP9t4t"}, {"id": "418", "title": "Le soleil vers son d\u00e9clin", "url": "https://drive.google.com/uc?export=download&id=1q2nI1wev0O50Vk25vNFPYLpZ-A-gGIcc"}, {"id": "419", "title": "La nuit r\u00e9pand ses voiles...", "url": "https://drive.google.com/uc?export=download&id=1xYSCsXKZKZp-oN8RGAUFcPu97LNaGUPZ"}, {"id": "420", "title": "D\u00e9j\u00e0 l'\u00e9toile s'allume aux cieux", "url": "https://drive.google.com/uc?export=download&id=1A0EQZbz6uF3n1SgfRBIPpzTNLRNUQxkv"}, {"id": "421", "title": "O notre Dieu...", "url": "https://drive.google.com/uc?export=download&id=1oqD46b03UXjh7TrRway6F60eysFDeNsY"}, {"id": "422", "title": "Ainsi que d'une lyre", "url": "https://drive.google.com/uc?export=download&id=1tbzqR2J0J2-VLD7JJ2_sVyI-G5N0l4AJ"}, {"id": "423", "title": "Au seuil de chaque ann\u00e9e", "url": "https://drive.google.com/uc?export=download&id=1tM3i-D5uZt-62NxK7Pq5dnegC7lbpwal"}, {"id": "424", "title": "Nos fugitives ann\u00e9es", "url": "https://drive.google.com/uc?export=download&id=1Y-gXK9uRzGV8L92e6dz8ejqVLudB650n"}, {"id": "425", "title": "O Dieu, que cette ann\u00e9e", "url": "https://drive.google.com/uc?export=download&id=1SxOJMdHgLF36tzvyEuFxBt9vdqgdI8Xh"}, {"id": "426", "title": "O Seigneur, \u00c9ternel!", "url": "https://drive.google.com/uc?export=download&id=1uM2pdX_28zi2pRZo6uKJbwgHfuozcCso"}, {"id": "427", "title": "C'est de toi, Dieu puissant...", "url": "https://drive.google.com/uc?export=download&id=1uM2pdX_28zi2pRZo6uKJbwgHfuozcCso"}, {"id": "428", "title": "P\u00e8re saint, dont la cl\u00e9mence", "url": "https://drive.google.com/uc?export=download&id=1YFEXmiNPzLGFKP4HJE4ETBtprUjt9oOD"}, {"id": "429", "title": "Sur ces \u00e9poux, P\u00e8re \u00e9ternel", "url": "https://drive.google.com/uc?export=download&id=1z2ERkUZ9P3-Auvc4jvcp2d3ltoJbbZI-"}, {"id": "430", "title": "Sur ces \u00e9poux, Seigneur...", "url": "https://drive.google.com/uc?export=download&id=1Gh89g13dY90MFPU0wpkJoPG1JpKEKGVk"}, {"id": "431", "title": "Qu'elle est douce, l'harmonie!", "url": "https://drive.google.com/uc?export=download&id=177v-ZiAIqW9QdefYXyUQO513jnF5Fl9R"}, {"id": "432", "title": "On est bien \u00e0 la maison", "url": "https://drive.google.com/uc?export=download&id=1toEDChD4hLTut-N_WTK5OqeSq5QDvRqu"}, {"id": "434", "title": "Quel bonheur d'\u00eatre en famille", "url": "https://drive.google.com/uc?export=download&id=1Kjp3DvDgwHCtAZD6VSCdLztIPw8DhkeJ"}, {"id": "435", "title": "Qu'il fait bon", "url": "https://drive.google.com/uc?export=download&id=1HKU4GhfF6HND4YycNEM0Qhn5GEn9yEpM"}, {"id": "436", "title": "Travailleur, voici le soir", "url": "https://drive.google.com/uc?export=download&id=12feZ7N7q_MPPh_4TEoGIZPQ9ryHcKWia"}, {"id": "437", "title": "Cloches, sonnez!", "url": "https://drive.google.com/uc?export=download&id=13JHzngswyv0g37XW6kkqFPifF3EY5lRD"}, {"id": "438", "title": "Oh! pendant que pour eux", "url": "https://drive.google.com/uc?export=download&id=1vxAC-rDxz1wpYbCJcdsHMJz_ON-jgACG"}, {"id": "439", "title": "O Pasteur \u00e9ternel", "url": "https://drive.google.com/uc?export=download&id=17HglNAhS1uj4Th1bHY3ZiIutHX-1USMG"}, {"id": "440", "title": "Un nouveau combattant", "url": "https://drive.google.com/uc?export=download&id=1Ik4_xToKUIyIGqqNjPEMhYZXgZs24nJG"}, {"id": "441", "title": "A toi, Seigneur, en ce beau jour", "url": "https://drive.google.com/uc?export=download&id=1xqc6t19laF9dpkVcUERgduBD9EyZeB99"}, {"id": "442", "title": "O jour heureux!", "url": "https://drive.google.com/uc?export=download&id=11kJPX0YNbG3pARR9qDnlSdn7EmyKll5k"}, {"id": "443", "title": "Dans ce grand jour", "url": "https://drive.google.com/uc?export=download&id=1w4d8DsP7qw8d_Uc5NMUToO9jmjchEc4w"}, {"id": "444", "title": "Toi dont les cieux des cieux...", "url": "https://drive.google.com/uc?export=download&id=1dnNgyYPoFkGYJcVrovoK1RhAag3k9IJS"}, {"id": "445", "title": "C'est l'heure, amis...", "url": "https://drive.google.com/uc?export=download&id=14Myrsk9T9DKYKgDiuSSlOIlY-xIrUQ5Y"}, {"id": "446", "title": "J\u00e9sus soit avec vous", "url": "https://drive.google.com/uc?export=download&id=1cdat4neCMa8u9XuboJ0VWcdLjet62N3g"}, {"id": "447", "title": "Reverra-t-il cette terre ch\u00e9rie?", "url": "https://drive.google.com/uc?export=download&id=1cX_SgMPXKIz-o_Q4IDUvI34ekFBxevxD"}, {"id": "449", "title": "Nous mourrons, mais pour rena\u00eetre", "url": "https://drive.google.com/uc?export=download&id=1A9IGOq4BzyHU-dFqbxql8tdgVXroatZv"}, {"id": "450", "title": "Douleur profonde", "url": "https://drive.google.com/uc?export=download&id=1lcKR5eq4k8QfUYFDKSQLWSugcKxg6dl2"}, {"id": "451", "title": "Plus haut que l'azur des cieux", "url": "https://drive.google.com/uc?export=download&id=1ypucPPVv54nQSRbZRZYJz3rAb_wl3VLj"}, {"id": "452", "title": "Pourquoi reprendre", "url": "https://drive.google.com/uc?export=download&id=1XSUyMuFDTDwwoLARGloTA3MW0KF1cLK3"}, {"id": "453", "title": "Plus de pleurs...", "url": "https://drive.google.com/uc?export=download&id=1kIL_QjWFsRUvWICcDThQMrHo7hyFfhvx"}, {"id": "454", "title": "Malheureuse famille", "url": "https://drive.google.com/uc?export=download&id=1MnZd9nL5HZlFvtiSlJjWqyHPaTbm0W-w"}, {"id": "455", "title": "G\u00e9missant sous l'esclavage", "url": "https://drive.google.com/uc?export=download&id=1joPGBBNmfnzHHx5P82B_EW4hCUB0i3Rt"}, {"id": "456", "title": "La route est glissante", "url": "https://drive.google.com/uc?export=download&id=14tobhRFDoMNCc1BDxNH0SCjKK0x2v7jM"}, {"id": "457", "title": "Pauvre buveur!", "url": "https://drive.google.com/uc?export=download&id=1-4ofpzxhE6PRxcrsignQiAegsLCa20hE"}, {"id": "459", "title": "Venez captifs", "url": "https://drive.google.com/uc?export=download&id=157Xn34Ja8anpm4Hxe-LyTNCOY2Y_52xg"}, {"id": "460", "title": "Ah! sous ton rire...", "url": "https://drive.google.com/uc?export=download&id=1JSJQ7b93ms6trf84SIPbgvM4-EhrvSvN"}, {"id": "461", "title": "Aux jours d'angoisse", "url": "https://drive.google.com/uc?export=download&id=1oelkRQpI7mi8vyv8quxZ6Vf61ea0aI-i"}, {"id": "462", "title": "D\u00e8s le printemps de ta vie", "url": "https://drive.google.com/uc?export=download&id=1ZPVQdoeG5zyKhfLvbtckzWbS-4yYdewr"}, {"id": "463", "title": "Dans la joie et l'all\u00e9gresse", "url": "https://drive.google.com/uc?export=download&id=1lGhwYJtO4ATc4wTygTOsTlb4qUT4CMyc"}, {"id": "464", "title": "Entends l'\u00e9cho de la voix", "url": "https://drive.google.com/uc?export=download&id=1r1Dd5XILqgO0Js543Qp11_fYpQd3hNG_"}, {"id": "465", "title": "Es-tu lass\u00e9...", "url": "https://drive.google.com/uc?export=download&id=178WA3fcmlOy6E-mK16SXERHmvq5hVquB"}, {"id": "466", "title": "Laisse ta folie", "url": "https://drive.google.com/uc?export=download&id=1SijoZ9tY3mOFPzkVVOVb0T4VrmpBILgj"}, {"id": "468", "title": "Maintes fois", "url": "https://drive.google.com/uc?export=download&id=1Nj3HBynpFvDtPlxlGqLEe07OqIQxSFfF"}, {"id": "469", "title": "Mot que l'on aime entendre", "url": "https://drive.google.com/uc?export=download&id=1hXV8ZDTHVjV0NJN9B_zF6GxDWxXE9SyD"}, {"id": "470", "title": "Pourquoi la tristesse", "url": "https://drive.google.com/uc?export=download&id=1d8gKWnv2XlAGzrh76mv4Yx3r460yQej8"}, {"id": "471", "title": "Oh! viens \u00e0 moi", "url": "https://drive.google.com/uc?export=download&id=1Lc2_VsvmPWmNxWvRLZ9bCe8YEY9gIykW"}, {"id": "472", "title": "Sur le seuil", "url": "https://drive.google.com/uc?export=download&id=1NdZMBVcYxKuh5PJKi337vxxutRZwQr2n"}, {"id": "474", "title": "Pendant les jours de ta jeunesse", "url": "https://drive.google.com/uc?export=download&id=1qm-LXEplxTxAsD5duJHcnkMsIu0DIvN_"}, {"id": "475", "title": "Pourquoi donc attendre", "url": "https://drive.google.com/uc?export=download&id=19roDZoe3igpcvHerT0UaQ0eJZ--Wx0Ax"}, {"id": "479", "title": "Viens, viens \u00e0 J\u00e9sus!", "url": "https://drive.google.com/uc?export=download&id=1gfw_vWEubERjEt4-H7nZo26-iCb5CY4f"}, {"id": "480", "title": "Voici, je me tiens \u00e0 la porte", "url": "https://drive.google.com/uc?export=download&id=1Inzxf_MfojqwSHGTvN_kG3b5AeWLKc_r"}, {"id": "481", "title": "A toi ma vie!", "url": "https://drive.google.com/uc?export=download&id=1lO7vFLLV3uPYqJf-XC7iKCnvU31xGo8B"}, {"id": "482", "title": "Au combat de la vie", "url": "https://drive.google.com/uc?export=download&id=1887KfQeuLVbU_2Qt5MFIanyH2z5ELvPT"}, {"id": "484", "title": "Il faut que mon coeur chante!", "url": "https://drive.google.com/uc?export=download&id=1SqtxUxvZJ9yVapjOYFTNsvd_UiKWiR_q"}, {"id": "485", "title": "Ce que J\u00e9sus-Christ nous demande", "url": "https://drive.google.com/uc?export=download&id=1g8KhSmgYDL62tzyQZLijx3776ZrjmE4G"}, {"id": "486", "title": "Des paroles de charmes", "url": "https://drive.google.com/uc?export=download&id=18DVRMhyjWF7k8BCoP-4CHclzKm1GHS2e"}, {"id": "487", "title": "Choisir J\u00e9sus d\u00e8s la jeunesse", "url": "https://drive.google.com/uc?export=download&id=1yNYj-Rjfbu4-mbmu7S4Qflis4kapBXx1"}, {"id": "488", "title": "Comme un enfant...", "url": "https://drive.google.com/uc?export=download&id=17pKfsyBWOASPff5eCIsPhzjdsqLVCi-f"}, {"id": "489", "title": "Entre tes mains, j'abandonne", "url": "https://drive.google.com/uc?export=download&id=1SEspMJZP9w1YFmTGIQVtI3vZwySF1DlJ"}, {"id": "490", "title": "Entendez-vous l'appel du Ma\u00eetre?", "url": "https://drive.google.com/uc?export=download&id=1CRt0CL1HOqsO6zr5WF28Oz5lb7iqLTtP"}, {"id": "491", "title": "Je m'approche de toi", "url": "https://drive.google.com/uc?export=download&id=1O9PYWS267S0HhLAUjo1TlLzCMcwF_p0Z"}, {"id": "492", "title": "En ce monde de tristesse", "url": "https://drive.google.com/uc?export=download&id=1RorK4csh-Fi0LB9BD1fZCxMjgOOjIzhj"}, {"id": "493", "title": "Mon coeur te cherche...", "url": "https://drive.google.com/uc?export=download&id=1qX-C2nzyzTcMvIiGHkPHsjQgoqaeHxc4"}, {"id": "494", "title": "J\u00e9sus, doux Ma\u00eetre", "url": "https://drive.google.com/uc?export=download&id=1iVVuav3lPvBbG4ckVeF4pUSK6FX0N31B"}, {"id": "495", "title": "La voix du Seigneur m'appelle", "url": "https://drive.google.com/uc?export=download&id=1oLp45YD965V_KpO82HSw7bztsd16B4p8"}, {"id": "496", "title": "J'entends ta douce voix", "url": "https://drive.google.com/uc?export=download&id=1aGEydjcHI6v7M4of7MfxIsgtw1clGYWc"}, {"id": "497", "title": "Je suis \u00e0 toi, mon Dieu...", "url": "https://drive.google.com/uc?export=download&id=1piVGo1jnmybAmhpu4qg4m13N1AprQcZP"}, {"id": "498", "title": "Jeunesse ardente", "url": "https://drive.google.com/uc?export=download&id=1M0Nc8BDVR2z098HW9pDPSuWC8KEvnFyQ"}, {"id": "499", "title": "Mon coeur tressaille \u00e0 ta voix", "url": "https://drive.google.com/uc?export=download&id=1ousQ_s-YGNJAEshOXUKaCX0s9xPoAwDK"}, {"id": "500", "title": "J\u00e9sus, je te suivrai partout", "url": "https://drive.google.com/uc?export=download&id=1RH7NIBoF8JTrooIjl-ToGbyyVbYTQlkF"}, {"id": "503", "title": "O toi qui donnes la vie", "url": "https://drive.google.com/uc?export=download&id=1APM1dQXNrrdZ-ocuSS8jaUJP5ZnyrIb5"}, {"id": "508", "title": "Seigneur, mon \u00e2me soupire", "url": "https://drive.google.com/uc?export=download&id=1V0co2Or0wM-BAEJLJT2AGggvPDgOpVfS"}, {"id": "516", "title": "Quand sur ma t\u00eate...", "url": "https://drive.google.com/uc?export=download&id=1YvW6is42hy0lei6MNKFDGtc5W3m9JhHM"}, {"id": "518", "title": "Je l'ai trouv\u00e9!", "url": "https://drive.google.com/uc?export=download&id=1tsVVnumdltkKSFvmIoW4YtMnShkmlAX4"}, {"id": "519", "title": "Joie au ciel!", "url": "https://drive.google.com/uc?export=download&id=1O6NCtUV53wqRH0DykxvghcVl3H-go9NL"}, {"id": "521", "title": "Mortels, voulez-vous savoir", "url": "https://drive.google.com/uc?export=download&id=1W7GJd5axzQ9-N3Gd4aZtf8lkgpwpTVBE"}, {"id": "522", "title": "Ne crains rien, je t'aime", "url": "https://drive.google.com/uc?export=download&id=1BVLvKdCaKjESH7XzuHduQk45FKJclkEn"}, {"id": "523", "title": "Oui, tout est bien", "url": "https://drive.google.com/uc?export=download&id=1w93JkZHZKoiCp3W70DyeUFK_jofjql66"}, {"id": "524", "title": "Pour toi qu'un tourment oppresse", "url": "https://drive.google.com/uc?export=download&id=1P2mmSAnpAt2CDTyJ0vht7DXJNJbQredt"}, {"id": "525", "title": "Pour la c\u00e9leste cit\u00e9, dites-moi", "url": "https://drive.google.com/uc?export=download&id=1Wb4ygvtKsA1tzguNBSRdDmjXPzxC-SmI"}, {"id": "528", "title": "Toute cha\u00eene est enlev\u00e9e", "url": "https://drive.google.com/uc?export=download&id=1cM9xJ_8fAs4GCBq3qpy6Es_BhCmqyFFw"}, {"id": "530", "title": "Debout, volontaires!", "url": "https://drive.google.com/uc?export=download&id=1vDpbf_AqOIMi8nBbbzKbG2DlwMpZgmnc"}, {"id": "531", "title": "Ecoutez l'appel du berger!", "url": "https://drive.google.com/uc?export=download&id=1HLcAdDS5K0l0M0T-36VlbHIqZfBmTyoY"}, {"id": "532", "title": "Entends-tu l'appel du Ma\u00eetre?", "url": "https://drive.google.com/uc?export=download&id=1unH_JSZgUvDEI1beqK377p-Yj7yucisz"}, {"id": "533", "title": "La voix de tes sentinelles", "url": "https://drive.google.com/uc?export=download&id=1mKhjEpp8DKNIpY6_rVnZ6J-CdOaweznp"}, {"id": "534", "title": "Messagers du grand Roi", "url": "https://drive.google.com/uc?export=download&id=1t36G7QCUGb1vE7-hgZtKIEsrK06a_sQF"}, {"id": "535", "title": "Seigneur, que la terre enti\u00e8re", "url": "https://drive.google.com/uc?export=download&id=1qtp_ljR5AgaZUrwirG0bgPOW8pGY1WbL"}, {"id": "536", "title": "Sentinelle vigilante", "url": "https://drive.google.com/uc?export=download&id=1ma0lCLBvQqdiX-_GmejjUoWFVtqToNWW"}, {"id": "537", "title": "Rev\u00eats tes armes, volontaire!", "url": "https://drive.google.com/uc?export=download&id=1TQj18cPpi3IsGX3SfRsz-nk2KsoB8I32"}, {"id": "539", "title": "Travaillons tous pour notre Ma\u00eetre", "url": "https://drive.google.com/uc?export=download&id=1sfg80-UZ7PiWLJmXHNd5B4d_Z0WQWQ2i"}, {"id": "541", "title": "Volontaires, au combat!", "url": "https://drive.google.com/uc?export=download&id=1t8P5cj6gAYzhMamK3HNK-aJWmgYOaSxZ"}, {"id": "543", "title": "Amis, chantons ensemble", "url": "https://drive.google.com/uc?export=download&id=1U8HA2kAKxc6vGCgEXKrGxMPCCOT5BRGP"}, {"id": "554", "title": "As-tu compt\u00e9...", "url": "https://drive.google.com/uc?export=download&id=1WeJuGniYvKg7L3LLhpt6zXBgqg99dbu9"}, {"id": "555", "title": "Cherchons d\u00e8s l'enfance", "url": "https://drive.google.com/uc?export=download&id=1wzplVFVHLmug9TKlVRqUa6HJdYPtuHr8"}, {"id": "557", "title": "Enfants, soyez sages", "url": "https://drive.google.com/uc?export=download&id=15cbvzifmBiH1-Fho1EXXwalWZycqCeRi"}, {"id": "560", "title": "J\u00e9sus est au milieu de nous", "url": "https://drive.google.com/uc?export=download&id=11WKeWbdGdanQ2r9-eGTkd1g0vzRnbWBB"}, {"id": "562", "title": "J'aime \u00e0 penser...", "url": "https://drive.google.com/uc?export=download&id=1nATEJOssNKeFnjCy10WKGMYJ7Cfuwzky"}, {"id": "567", "title": "David n'avait rien que sa fronde", "url": "https://drive.google.com/uc?export=download&id=1l7BeBhnlhTmxHMv7FRQhNkcKAOEj7Sbn"}, {"id": "569", "title": "Mon Sauveur, c'est par la foi", "url": "https://drive.google.com/uc?export=download&id=1-INO48YuJY5T9rNVJq-Jj9QSihmjVdjr"}, {"id": "570", "title": "La bande joyeuse", "url": "https://drive.google.com/uc?export=download&id=1f93tyKSs6ulK2D6raOHsTSwGSgUhv1FC"}, {"id": "572", "title": "Nul enfant n'est trop petit...", "url": "https://drive.google.com/uc?export=download&id=1fa1gsMZYSxP8OdLBpboYwhevKRQpElKh"}, {"id": "574", "title": "Tant qu'il vit", "url": "https://drive.google.com/uc?export=download&id=1-CI3daAhfJEEWcYGTplRNw6D_JbHt_tH"}, {"id": "576", "title": "Pour chanter les louanges", "url": "https://drive.google.com/uc?export=download&id=1OENWOd1dQyz1wlfGHRjXC1Rcvib714zU"}, {"id": "577", "title": "Que je sois...", "url": "https://drive.google.com/uc?export=download&id=1Lx9NQUQh38lUNkoJ1ea-sHcqmK18d-nX"}, {"id": "579", "title": "Toi qui veux \u00eatre notre fr\u00e8re", "url": "https://drive.google.com/uc?export=download&id=1jfNeGUOGKTagHuWms3VsWV49Xi8nQMqG"}, {"id": "580", "title": "A ton \u00e9cole", "url": "https://drive.google.com/uc?export=download&id=1eXNp68TP-22QflVOqs9rs6B23HLGxpkK"}, {"id": "581", "title": "Douce cloche, chante...", "url": "https://drive.google.com/uc?export=download&id=1OIzvE9T1R33byOi3YutBGqe2SyEeI_zT"}, {"id": "582", "title": "Entrons \u00e0 l'\u00e9cole", "url": "https://drive.google.com/uc?export=download&id=15C1X11Vs_0sLxxGu3Zs-f-OPmjccLF46"}, {"id": "583", "title": "Sortons de l'\u00e9cole", "url": "https://drive.google.com/uc?export=download&id=1Iev1q2nsOeEmfS6OwP4R-rlI2Xn4WGc7"}, {"id": "584", "title": "Seigneur, de ta demeure", "url": "https://drive.google.com/uc?export=download&id=1meWRWnPoATkzdc33JcWXqLJOekpiwK_c"}, {"id": "585", "title": "Tinte, pi\u00e8ce blanche!", "url": "https://drive.google.com/uc?export=download&id=1SnLKqGl5uB_addhEPF4rC4e0gLEhD1nO"}, {"id": "586", "title": "Oh! que ta main paternelle", "url": "https://drive.google.com/uc?export=download&id=1hBfnkYHjiBxL30vpcwCH93Dxon5huo2w"}, {"id": "587", "title": "L'ombre \u00e9tend ses voiles", "url": "https://drive.google.com/uc?export=download&id=1oLKiJpy_CyHAPmGm2OyiUK1OSWik80g5"}, {"id": "588", "title": "Si du nid tombe l'oisillon", "url": "https://drive.google.com/uc?export=download&id=1F9bXWZ3CCtMaG4C0nBB0ld2bp9m15pns"}, {"id": "589", "title": "L'ombre descend de la colline", "url": "https://drive.google.com/uc?export=download&id=11TfBjni0aIjnpxBEXYGj2g4wz7Rm_fZm"}, {"id": "591", "title": "Palais d'ivoire", "url": "https://drive.google.com/uc?export=download&id=1yfuVuWBKqYe2X7alHh5prOA-2JT2BBFg"}, {"id": "592", "title": "Connais-tu cette cit\u00e9", "url": "https://drive.google.com/uc?export=download&id=1u7obo-Qv6BnKoAmtnZw-ekXDAPYoRU2F"}, {"id": "593", "title": "Dans le jardin o\u00f9 j'aime entrer", "url": "https://drive.google.com/uc?export=download&id=1Fm07j7lR578iPPWDqVhdpRrTuXU1u1-d"}, {"id": "594", "title": "Au s\u00e9jour des bienheureux", "url": "https://drive.google.com/uc?export=download&id=15Kwl2FUvNHOAdxFTtehi4VGLjcrlUQRv"}, {"id": "595", "title": "Entends la voix du Sauveur ...", "url": "https://drive.google.com/uc?export=download&id=1ZAhNqRSLIBRPWOpqYtg7LQx4eP-enNvA"}, {"id": "596", "title": "Flots mugissants...", "url": "https://drive.google.com/uc?export=download&id=1GnAjS2vqX3VEANBgBWhumTZOdJreNrq8"}, {"id": "597", "title": "Le Fils de Dieu...", "url": "https://drive.google.com/uc?export=download&id=1kEpQjbo7PmCr9GDQfKGLfa-KJfSyzfre"}, {"id": "598", "title": "Il faisait nuit...", "url": "https://drive.google.com/uc?export=download&id=1Kplr0O-UpBxh6z-s_2F9t3_0lGbxCOsT"}, {"id": "599", "title": "Meurs! \u00f4 J\u00e9sus...", "url": "https://drive.google.com/uc?export=download&id=1cXuujr72126fSHxtDaefizrA6p9IQYCI"}, {"id": "600", "title": "Le ciel p\u00e2lit \u00e0 l'orient", "url": "https://drive.google.com/uc?export=download&id=12flanRg-Uo0Cu1d07Z40mSxtIT_vU2Mo"}, {"id": "602", "title": "Tu payas mon salut...", "url": "https://drive.google.com/uc?export=download&id=1FEbKoz0eAwjEiqMFFC2BGC7XspPG71tq"}, {"id": "603", "title": "Seigneur, que n'ai-je mille voix!", "url": "https://drive.google.com/uc?export=download&id=1QcXBbK6zzZAW01Klwq_eY72PyYgbNlzF"}, {"id": "606", "title": "Gloire \u00e0 mon Dieu!", "url": "https://drive.google.com/uc?export=download&id=1Ptbh1BNfnQoV4_LlDfE_CMTjir22Ds_N"}, {"id": "607", "title": "J\u00e9sus m'entend...", "url": "https://drive.google.com/uc?export=download&id=1q3hGR3Z2Rs7ycqkxjrV_UoTY9bMVCk3x"}, {"id": "608", "title": "On frappe...", "url": "https://drive.google.com/uc?export=download&id=1I7P5_0ic2SWMEj8thtceIibYeWiy5lVg"}, {"id": "611", "title": "Sur mon chemin...", "url": "https://drive.google.com/uc?export=download&id=17XcJWXDNDtLpc1lHQdHRwrpc1dDAT7CJ"}, {"id": "612", "title": "Dieu, mon p\u00e9ch\u00e9 me d\u00e9sole!", "url": "https://drive.google.com/uc?export=download&id=1OYZF-eFdU5J_ZrSDGA8lXNU_djgiCK3O"}, {"id": "613", "title": "Le Colporteur Vaudois", "url": "https://drive.google.com/uc?export=download&id=1xqqj_cI9FH9kPTHK9RQsQt31FLT1nUGD"}, {"id": "614", "title": "Dans Sion, pays de gloire", "url": "https://drive.google.com/uc?export=download&id=1Z9BTalet42KxKX0Ppsk5_kMAHWud8xfQ"}, {"id": "615", "title": "O toi, source intarissable", "url": "https://drive.google.com/uc?export=download&id=1GKnYHtKiA9mPUqIoPA2CLqipyg6yL27q"}, {"id": "616", "title": "Nuit sans espoir", "url": "https://drive.google.com/uc?export=download&id=1Sc0eMd58jr0Anpi6zRQQAnAxYon7c0iB"}, {"id": "617", "title": "L'\u00c9ternel seul est Seigneur", "url": "https://drive.google.com/uc?export=download&id=14sVUB2Hfgrx4Ony2upK5YTBqqB5JDOP5"}, {"id": "619", "title": "Chr\u00e9tiens, voici le R\u00e9dempteur!", "url": "https://drive.google.com/uc?export=download&id=131cFSTAZspgJH5SXsPA_rSeAK-fvqmG2"}, {"id": "621", "title": "Christ va venir", "url": "https://drive.google.com/uc?export=download&id=1oN9_rk1PjxS72uM4uH901jfX8i_Qk0sM"}, {"id": "622", "title": "Confiance", "url": "https://drive.google.com/uc?export=download&id=1EMr46LCH3uYukN93VMZyFdCpQUxUHQTd"}, {"id": "623", "title": "Enfants de lumi\u00e8re", "url": "https://drive.google.com/uc?export=download&id=14Ts07AtPtLHPPP2Bda7Uv2MQ7cFI7BMx"}, {"id": "625", "title": "Les cieux en coeur", "url": "https://drive.google.com/uc?export=download&id=1fgLLq7zLiFaPEGYiwnqsqLsv0zhqbcqc"}, {"id": "628", "title": "La P\u00e2que", "url": "https://drive.google.com/uc?export=download&id=1Ny9d79RYbs4TJOY80QHsbRoh31QmvAXz"}, {"id": "629", "title": "O Dieu puissant", "url": "https://drive.google.com/uc?export=download&id=1Y0OBaU196D7rumSxtdwyMxie5780az_U"}, {"id": "631", "title": "J\u00e9rusalem, cit\u00e9 des cieux", "url": "https://drive.google.com/uc?export=download&id=1s0q0QPOS0BkmujZmWGNUhlWFkv3ZCOj4"}, {"id": "632", "title": "O notre P\u00e8re", "url": "https://drive.google.com/uc?export=download&id=15XcaFVXHgpoXcbiFW--4U8h86hTJ6hNa"}, {"id": "633", "title": "Sur tes murs...", "url": "https://drive.google.com/uc?export=download&id=1xNyep-ep4tJa64JRQ-bMaDhbFwoEH3Ah"}, {"id": "636", "title": "Qu'il est beau, mon pays!", "url": "https://drive.google.com/uc?export=download&id=1r0aoKZ_CkJsfQpIC8jCmM0W9KkxX0IZe"}, {"id": "637", "title": "Sur nos monts", "url": "https://drive.google.com/uc?export=download&id=1AK_RxGJVe7rRMZPwflkgP0GYi0w2wJbL"}, {"id": "638", "title": "Je veux r\u00e9pondre, \u00f4 Dieu!", "url": "https://drive.google.com/uc?export=download&id=1EQWXfCnpZlg9yeFuEP50Am8N93uwwilB"}, {"id": "640", "title": "Au sein de la nuit...", "url": "https://drive.google.com/uc?export=download&id=1wCK0DVq6shlOuMgoXFutDi6UavZLoi-o"}, {"id": "651", "title": "Saint des saints...", "url": "https://drive.google.com/uc?export=download&id=13p6ZJUIMB3fycqQ0riL_UmpSxLx_DaKy"}, {"id": "652", "title": "Quand la nuit \u00e9tend son voile", "url": "https://drive.google.com/uc?export=download&id=175LQYsA2-xZujrq0RA56u8uDHHhfL5H2"}, {"id": "653", "title": "Chant du soir", "url": "https://drive.google.com/uc?export=download&id=1-5GEHIbrIGBGYB81bMz4SSEn5bZi_ddB"}, {"id": "654", "title": "Nuit b\u00e9nie, douce nuit!", "url": "https://drive.google.com/uc?export=download&id=1niT_ZythVtM3H87QsCdZfbdEEI4u0RV4"}]