[
  {
    "id": "vop_kiE3Wt1v_1o",
    "title": "VOP Family Reunion - Part 1",
    "description": "Voice of Prophecy",
    "url": "https://www.youtube.com/watch?v=kiE3Wt1v_1o",
    "isWebStream": false,
    "image": "https://img.youtube.com/vi/kiE3Wt1v_1o/hqdefault.jpg"
  },
  {
    "id": "vop_GuvLiqccgtY",
    "title": "VOP Family Reunion - Part 2",
    "description": "Voice of Prophecy",
    "url": "https://www.youtube.com/watch?v=GuvLiqccgtY",
    "isWebStream": false,
    "image": "https://img.youtube.com/vi/GuvLiqccgtY/hqdefault.jpg"
  },
  {
    "id": "vop_cxAX8DGF0ng",
    "title": "VOP Family Reunion - Part 3",
    "description": "Voice of Prophecy",
    "url": "https://www.youtube.com/watch?v=cxAX8DGF0ng",
    "isWebStream": false,
    "image": "https://img.youtube.com/vi/cxAX8DGF0ng/hqdefault.jpg"
  },
  {
    "id": "vop_mMe9jGtURG4",
    "title": "VOP Family Reunion - Part 4",
    "description": "Voice of Prophecy",
    "url": "https://www.youtube.com/watch?v=mMe9jGtURG4",
    "isWebStream": false,
    "image": "https://img.youtube.com/vi/mMe9jGtURG4/hqdefault.jpg"
  },
  {
    "id": "vop_f5uiB2yglDg",
    "title": "VOP Family Reunion - Part 5",
    "description": "Voice of Prophecy",
    "url": "https://www.youtube.com/watch?v=f5uiB2yglDg",
    "isWebStream": false,
    "image": "https://img.youtube.com/vi/f5uiB2yglDg/hqdefault.jpg"
  },
  {
    "id": "vop_MJi5lLfEMpg",
    "title": "VOP Family Reunion - Part 6",
    "description": "Voice of Prophecy",
    "url": "https://www.youtube.com/watch?v=MJi5lLfEMpg",
    "isWebStream": false,
    "image": "https://img.youtube.com/vi/MJi5lLfEMpg/hqdefault.jpg"
  },
  {
    "id": "vop_lAIdT5lNkfg",
    "title": "VOP Family Reunion - Part 7",
    "description": "Voice of Prophecy",
    "url": "https://www.youtube.com/watch?v=lAIdT5lNkfg",
    "isWebStream": false,
    "image": "https://img.youtube.com/vi/lAIdT5lNkfg/hqdefault.jpg"
  },
  {
    "id": "vop_FlxbaTgDcEc",
    "title": "VOP Family Reunion - Part 8",
    "description": "Voice of Prophecy",
    "url": "https://www.youtube.com/watch?v=FlxbaTgDcEc",
    "isWebStream": false,
    "image": "https://img.youtube.com/vi/FlxbaTgDcEc/hqdefault.jpg"
  },
  {
    "id": "vop_0ha1r2CGqbU",
    "title": "VOP Family Reunion - Part 9",
    "description": "Voice of Prophecy",
    "url": "https://www.youtube.com/watch?v=0ha1r2CGqbU",
    "isWebStream": false,
    "image": "https://img.youtube.com/vi/0ha1r2CGqbU/hqdefault.jpg"
  },
  {
    "id": "vop_0H4VZGGzzZc",
    "title": "VOP Family Reunion - Part 10",
    "description": "Voice of Prophecy",
    "url": "https://www.youtube.com/watch?v=0H4VZGGzzZc",
    "isWebStream": false,
    "image": "https://img.youtube.com/vi/0H4VZGGzzZc/hqdefault.jpg"
  },
  {
    "id": "vop_hVeMrN4ms3c",
    "title": "VOP Family Reunion - Part 11",
    "description": "Voice of Prophecy",
    "url": "https://www.youtube.com/watch?v=hVeMrN4ms3c",
    "isWebStream": false,
    "image": "https://img.youtube.com/vi/hVeMrN4ms3c/hqdefault.jpg"
  }
]
